Workbook
Name CATEGORIES: LISTS!$A$2:$A$19
Name SUBCATEGORIES: LISTS!$B$2:$B$54
Name PAYMENT_METHODS: LISTS!$C$2:$C$9
Name NEED_WANT: LISTS!$D$2:$D$5
Name YES_NO: LISTS!$E$2:$E$3
Name INCOME_SOURCES: LISTS!$F$2:$F$11
Name BILLING_CYCLES: LISTS!$G$2:$G$5
Name DEBT_TYPES: LISTS!$H$2:$H$10
Name PAID_STATUS: LISTS!$I$2:$I$4
Name SUB_STATUS: LISTS!$J$2:$J$4
Name CATEGORY_TYPE: LISTS!$K$2:$K$3
Name USER_NAME: 'START HERE'!$B$5
Name CURRENCY: 'START HERE'!$B$6
Name CURRENT_MONTH: 'START HERE'!$B$7
Name MONTHLY_INCOME: 'START HERE'!$B$8
Name SAVINGS_GOAL_PCT: 'START HERE'!$B$9
Name BudgetData: 'Monthly Budget'!$A$4:$K$103
Name ExpenseData: 'Expense Tracker'!$A$4:$M$503
Name IncomeData: 'Income Tracker'!$A$4:$K$103
Name GoalData: 'Savings Goals'!$A$4:$H$33
Name DebtData: 'Debt Tracker'!$A$4:$M$7
Name SinkingFundData: 'Sinking Funds'!$A$4:$I$15
Name SubscriptionData: 'Subscriptions'!$A$4:$H$15
Name BillsData: 'Bills Calendar'!$A$4:$L$18

Sheet LISTS
A1: Category | B1: Subcategory | C1: Payment_Method | D1: Need_Want | E1: Yes_No | F1: Income_Source | G1: Billing_Cycle | H1: Debt_Type | I1: Paid_Status | J1: Sub_Status | K1: Category_Type
A2: Housing | B2: Rent | C2: Cash | D2: Need | E2: Yes | F2: Salary | G2: Monthly | H2: Credit Card | I2: Yes | J2: Active | K2: Active
A3: Food & Dining | B3: Mortgage | C3: Debit Card | D3: Want | E3: No | F3: Freelance/Contract | G3: Annual | H3: Car Loan | I3: No | J3: Cancelled | K3: Passive
A4: Transportation | B4: Home Insurance | C4: Credit Card | D4: Investment | F4: Business Revenue | G4: Quarterly | H4: Student Loan | I4: Pending | J4: Paused
A5: Entertainment | B5: Repairs | C5: Bank Transfer | D5: Savings | F5: Rental Income | G5: Weekly | H5: Personal Loan
A6: Shopping | B6: HOA | C6: PayPal | F6: Dividends | H6: Medical Debt
A7: Healthcare | B7: Groceries | C7: Venmo | F7: Interest | H7: Mortgage
A8: Utilities | B8: Restaurants | C8: Check | F8: Refund | H8: Home Equity
A9: Education | B9: Coffee | C9: Other | F9: Gift | H9: Business Loan
A10: Personal Care | B10: Delivery | F10: Side Hustle | H10: Other
A11: Savings | B11: Gas | F11: Other
A12: Investments | B12: Car Insurance
A13: Debt Payment | B13: Maintenance
A14: Kids | B14: Parking
A15: Pets | B15: Public Transit
A16: Travel | B16: Streaming
A17: Subscriptions | B17: Movies
A18: Insurance | B18: Games
A19: Other | B19: Sports
B20: Hobbies
B21: Clothing
B22: Electronics
B23: Gifts
B24: Doctor
B25: Dental
B26: Pharmacy
B27: Vision
B28: Electricity
B29: Water
B30: Internet
B31: Phone
... B54: Other

Sheet Dashboard
A1: 🏠 Dashboard
A2: ="Welcome back, "&'START HERE'!B5&"! Here is your financial snapshot for "&'START HERE'!B7&"."
A3: ="📊 THIS MONTH AT A GLANCE — "&TEXT(TODAY(),"MMMM YYYY")
A4: 💰 Income This Month | C4: 💸 Expenses This Month | E4: 📈 Net This Month | G4: 🎯 Savings Rate | J4: Housing | K4: =SUMIFS('Expense Tracker'!E4:E503,'Expense Tracker'!C4:C503,J4,'Expense Tracker'!L4:L503,MONTH(TODAY()),'Expense Tracker'!M4:M503,YEAR(TODAY())) | L4: =IF('Bills Calendar'!G4="Yes",9999,'Bills Calendar'!I4) | N4: =IFERROR(IF(SMALL($L$4:$L$18,1)>=9999,0,MATCH(SMALL($L$4:$L$18,1),$L$4:$L$18,0)),0) | O4: =IFERROR(MATCH(LARGE('Expense Tracker'!$A$4:$A$503,1),'Expense Tracker'!$A$4:$A$503,0),0)
A5: =SUMIFS('Income Tracker'!G4:G103,'Income Tracker'!J4:J103,MONTH(TODAY()),'Income Tracker'!K4:K103,YEAR(TODAY())) | C5: =SUMIFS('Expense Tracker'!E4:E503,'Expense Tracker'!L4:L503,MONTH(TODAY()),'Expense Tracker'!M4:M503,YEAR(TODAY())) | E5: =A5-C5 | G5: =IFERROR(E5/A5,0) | J5: Food & Dining | K5: =SUMIFS('Expense Tracker'!E4:E503,'Expense Tracker'!C4:C503,J5,'Expense Tracker'!L4:L503,MONTH(TODAY()),'Expense Tracker'!M4:M503,YEAR(TODAY())) | L5: =IF('Bills Calendar'!G5="Yes",9999,'Bills Calendar'!I5) | N5: =IFERROR(IF(SMALL($L$4:$L$18,2)>=9999,0,MATCH(SMALL($L$4:$L$18,2),$L$4:$L$18,0)),0) | O5: =IFERROR(MATCH(LARGE('Expense Tracker'!$A$4:$A$503,2),'Expense Tracker'!$A$4:$A$503,0),0)
A6: 💳 Total Debt | C6: 🏆 Total Saved (Goals) | E6: 📅 Bills Due This Month | G6: 🔔 Unpaid Bills | J6: Transportation | K6: =SUMIFS('Expense Tracker'!E4:E503,'Expense Tracker'!C4:C503,J6,'Expense Tracker'!L4:L503,MONTH(TODAY()),'Expense Tracker'!M4:M503,YEAR(TODAY())) | L6: =IF('Bills Calendar'!G6="Yes",9999,'Bills Calendar'!I6) | N6: =IFERROR(IF(SMALL($L$4:$L$18,3)>=9999,0,MATCH(SMALL($L$4:$L$18,3),$L$4:$L$18,0)),0) | O6: =IFERROR(MATCH(LARGE('Expense Tracker'!$A$4:$A$503,3),'Expense Tracker'!$A$4:$A$503,0),0)
A7: =SUM('Debt Tracker'!D4:D7) | C7: ='Savings Goals'!B36 | E7: =SUM('Bills Calendar'!D4:D18) | G7: =COUNTIF('Bills Calendar'!G4:G18,"No") | J7: Entertainment | K7: =SUMIFS('Expense Tracker'!E4:E503,'Expense Tracker'!C4:C503,J7,'Expense Tracker'!L4:L503,MONTH(TODAY()),'Expense Tracker'!M4:M503,YEAR(TODAY())) | L7: =IF('Bills Calendar'!G7="Yes",9999,'Bills Calendar'!I7) | N7: =IFERROR(IF(SMALL($L$4:$L$18,4)>=9999,0,MATCH(SMALL($L$4:$L$18,4),$L$4:$L$18,0)),0) | O7: =IFERROR(MATCH(LARGE('Expense Tracker'!$A$4:$A$503,4),'Expense Tracker'!$A$4:$A$503,0),0)
J8: Shopping | K8: =SUMIFS('Expense Tracker'!E4:E503,'Expense Tracker'!C4:C503,J8,'Expense Tracker'!L4:L503,MONTH(TODAY()),'Expense Tracker'!M4:M503,YEAR(TODAY())) | L8: =IF('Bills Calendar'!G8="Yes",9999,'Bills Calendar'!I8) | O8: =IFERROR(MATCH(LARGE('Expense Tracker'!$A$4:$A$503,5),'Expense Tracker'!$A$4:$A$503,0),0)
A9: 📊 SPENDING BY CATEGORY (THIS MONTH) | E9: 🎯 SAVINGS GOALS PROGRESS | J9: Healthcare | K9: =SUMIFS('Expense Tracker'!E4:E503,'Expense Tracker'!C4:C503,J9,'Expense Tracker'!L4:L503,MONTH(TODAY()),'Expense Tracker'!M4:M503,YEAR(TODAY())) | L9: =IF('Bills Calendar'!G9="Yes",9999,'Bills Calendar'!I9)
A10: =IF(B10<=0,"—",INDEX($J$4:$J$21,MATCH(B10,$K$4:$K$21,0))) | B10: =LARGE($K$4:$K$21,1) | C10: =REPT("█",ROUND((IFERROR(MIN(B10/INDEX('Monthly Budget'!E4:E103,MATCH(A10,'Monthly Budget'!B4:B103,0)),1),0))*20,0))&REPT("░",20-ROUND((IFERROR(MIN(B10/INDEX('Monthly Budget'!E4:E103,MATCH(A10,'Monthly Budget'!B4:B103,0)),1),0))*20,0))&" "&TEXT(IFERROR(MIN(B10/INDEX('Monthly Budget'!E4:E103,MATCH(A10,'Monthly Budget'!B4:B103,0)),1),0),"0%") | E10: ='Savings Goals'!A4 | F10: =TEXT('Savings Goals'!B5,"$#,##0")&" / "&TEXT('Savings Goals'!F4,"$#,##0") | G10: ='Savings Goals'!A6 | J10: Utilities | K10: =SUMIFS('Expense Tracker'!E4:E503,'Expense Tracker'!C4:C503,J10,'Expense Tracker'!L4:L503,MONTH(TODAY()),'Expense Tracker'!M4:M503,YEAR(TODAY())) | L10: =IF('Bills Calendar'!G10="Yes",9999,'Bills Calendar'!I10)
A11: =IF(B11<=0,"—",INDEX($J$4:$J$21,MATCH(B11,$K$4:$K$21,0))) | B11: =LARGE($K$4:$K$21,2) | C11: =REPT("█",ROUND((IFERROR(MIN(B11/INDEX('Monthly Budget'!E4:E103,MATCH(A11,'Monthly Budget'!B4:B103,0)),1),0))*20,0))&REPT("░",20-ROUND((IFERROR(MIN(B11/INDEX('Monthly Budget'!E4:E103,MATCH(A11,'Monthly Budget'!B4:B103,0)),1),0))*20,0))&" "&TEXT(IFERROR(MIN(B11/INDEX('Monthly Budget'!E4:E103,MATCH(A11,'Monthly Budget'!B4:B103,0)),1),0),"0%") | E11: ='Savings Goals'!A9 | F11: =TEXT('Savings Goals'!B10,"$#,##0")&" / "&TEXT('Savings Goals'!F9,"$#,##0") | G11: ='Savings Goals'!A11 | J11: Education | K11: =SUMIFS('Expense Tracker'!E4:E503,'Expense Tracker'!C4:C503,J11,'Expense Tracker'!L4:L503,MONTH(TODAY()),'Expense Tracker'!M4:M503,YEAR(TODAY())) | L11: =IF('Bills Calendar'!G11="Yes",9999,'Bills Calendar'!I11)
A12: =IF(B12<=0,"—",INDEX($J$4:$J$21,MATCH(B12,$K$4:$K$21,0))) | B12: =LARGE($K$4:$K$21,3) | C12: =REPT("█",ROUND((IFERROR(MIN(B12/INDEX('Monthly Budget'!E4:E103,MATCH(A12,'Monthly Budget'!B4:B103,0)),1),0))*20,0))&REPT("░",20-ROUND((IFERROR(MIN(B12/INDEX('Monthly Budget'!E4:E103,MATCH(A12,'Monthly Budget'!B4:B103,0)),1),0))*20,0))&" "&TEXT(IFERROR(MIN(B12/INDEX('Monthly Budget'!E4:E103,MATCH(A12,'Monthly Budget'!B4:B103,0)),1),0),"0%") | E12: ='Savings Goals'!A14 | F12: =TEXT('Savings Goals'!B15,"$#,##0")&" / "&TEXT('Savings Goals'!F14,"$#,##0") | G12: ='Savings Goals'!A16 | J12: Personal Care | K12: =SUMIFS('Expense Tracker'!E4:E503,'Expense Tracker'!C4:C503,J12,'Expense Tracker'!L4:L503,MONTH(TODAY()),'Expense Tracker'!M4:M503,YEAR(TODAY())) | L12: =IF('Bills Calendar'!G12="Yes",9999,'Bills Calendar'!I12)
A13: =IF(B13<=0,"—",INDEX($J$4:$J$21,MATCH(B13,$K$4:$K$21,0))) | B13: =LARGE($K$4:$K$21,4) | C13: =REPT("█",ROUND((IFERROR(MIN(B13/INDEX('Monthly Budget'!E4:E103,MATCH(A13,'Monthly Budget'!B4:B103,0)),1),0))*20,0))&REPT("░",20-ROUND((IFERROR(MIN(B13/INDEX('Monthly Budget'!E4:E103,MATCH(A13,'Monthly Budget'!B4:B103,0)),1),0))*20,0))&" "&TEXT(IFERROR(MIN(B13/INDEX('Monthly Budget'!E4:E103,MATCH(A13,'Monthly Budget'!B4:B103,0)),1),0),"0%") | E13: ='Savings Goals'!A19 | F13: =TEXT('Savings Goals'!B20,"$#,##0")&" / "&TEXT('Savings Goals'!F19,"$#,##0") | G13: ='Savings Goals'!A21 | J13: Savings | K13: =SUMIFS('Expense Tracker'!E4:E503,'Expense Tracker'!C4:C503,J13,'Expense Tracker'!L4:L503,MONTH(TODAY()),'Expense Tracker'!M4:M503,YEAR(TODAY())) | L13: =IF('Bills Calendar'!G13="Yes",9999,'Bills Calendar'!I13)
A14: =IF(B14<=0,"—",INDEX($J$4:$J$21,MATCH(B14,$K$4:$K$21,0))) | B14: =LARGE($K$4:$K$21,5) | C14: =REPT("█",ROUND((IFERROR(MIN(B14/INDEX('Monthly Budget'!E4:E103,MATCH(A14,'Monthly Budget'!B4:B103,0)),1),0))*20,0))&REPT("░",20-ROUND((IFERROR(MIN(B14/INDEX('Monthly Budget'!E4:E103,MATCH(A14,'Monthly Budget'!B4:B103,0)),1),0))*20,0))&" "&TEXT(IFERROR(MIN(B14/INDEX('Monthly Budget'!E4:E103,MATCH(A14,'Monthly Budget'!B4:B103,0)),1),0),"0%") | E14: ='Savings Goals'!A24 | F14: =TEXT('Savings Goals'!B25,"$#,##0")&" / "&TEXT('Savings Goals'!F24,"$#,##0") | G14: ='Savings Goals'!A26 | J14: Investments | K14: =SUMIFS('Expense Tracker'!E4:E503,'Expense Tracker'!C4:C503,J14,'Expense Tracker'!L4:L503,MONTH(TODAY()),'Expense Tracker'!M4:M503,YEAR(TODAY())) | L14: =IF('Bills Calendar'!G14="Yes",9999,'Bills Calendar'!I14)
A15: =IF(B15<=0,"—",INDEX($J$4:$J$21,MATCH(B15,$K$4:$K$21,0))) | B15: =LARGE($K$4:$K$21,6) | C15: =REPT("█",ROUND((IFERROR(MIN(B15/INDEX('Monthly Budget'!E4:E103,MATCH(A15,'Monthly Budget'!B4:B103,0)),1),0))*20,0))&REPT("░",20-ROUND((IFERROR(MIN(B15/INDEX('Monthly Budget'!E4:E103,MATCH(A15,'Monthly Budget'!B4:B103,0)),1),0))*20,0))&" "&TEXT(IFERROR(MIN(B15/INDEX('Monthly Budget'!E4:E103,MATCH(A15,'Monthly Budget'!B4:B103,0)),1),0),"0%") | E15: ='Savings Goals'!A29 | F15: =TEXT('Savings Goals'!B30,"$#,##0")&" / "&TEXT('Savings Goals'!F29,"$#,##0") | G15: ='Savings Goals'!A31 | J15: Debt Payment | K15: =SUMIFS('Expense Tracker'!E4:E503,'Expense Tracker'!C4:C503,J15,'Expense Tracker'!L4:L503,MONTH(TODAY()),'Expense Tracker'!M4:M503,YEAR(TODAY())) | L15: =IF('Bills Calendar'!G15="Yes",9999,'Bills Calendar'!I15)
J16: Kids | K16: =SUMIFS('Expense Tracker'!E4:E503,'Expense Tracker'!C4:C503,J16,'Expense Tracker'!L4:L503,MONTH(TODAY()),'Expense Tracker'!M4:M503,YEAR(TODAY())) | L16: =IF('Bills Calendar'!G16="Yes",9999,'Bills Calendar'!I16)
A17: 💳 DEBT SNAPSHOT | E17: 📅 UPCOMING BILLS | J17: Pets | K17: =SUMIFS('Expense Tracker'!E4:E503,'Expense Tracker'!C4:C503,J17,'Expense Tracker'!L4:L503,MONTH(TODAY()),'Expense Tracker'!M4:M503,YEAR(TODAY())) | L17: =IF('Bills Calendar'!G17="Yes",9999,'Bills Calendar'!I17)
A18: ='Debt Tracker'!A4 | B18: ='Debt Tracker'!D4 | C18: ='Debt Tracker'!M4 | E18: =IF(N4=0,"🎉 All bills paid!",INDEX('Bills Calendar'!$A$4:$A$18,N4)&" — "&TEXT(INDEX('Bills Calendar'!$H$4:$H$18,N4),"MMM D")) | F18: =IF(N4=0,"",INDEX('Bills Calendar'!$D$4:$D$18,N4)) | G18: =IF(N4=0,"",INDEX('Bills Calendar'!$L$4:$L$18,N4)) | J18: Travel | K18: =SUMIFS('Expense Tracker'!E4:E503,'Expense Tracker'!C4:C503,J18,'Expense Tracker'!L4:L503,MONTH(TODAY()),'Expense Tracker'!M4:M503,YEAR(TODAY())) | L18: =IF('Bills Calendar'!G18="Yes",9999,'Bills Calendar'!I18)
A19: ='Debt Tracker'!A5 | B19: ='Debt Tracker'!D5 | C19: ='Debt Tracker'!M5 | E19: =IF(N5=0,"🎉 All bills paid!",INDEX('Bills Calendar'!$A$4:$A$18,N5)&" — "&TEXT(INDEX('Bills Calendar'!$H$4:$H$18,N5),"MMM D")) | F19: =IF(N5=0,"",INDEX('Bills Calendar'!$D$4:$D$18,N5)) | G19: =IF(N5=0,"",INDEX('Bills Calendar'!$L$4:$L$18,N5)) | J19: Subscriptions | K19: =SUMIFS('Expense Tracker'!E4:E503,'Expense Tracker'!C4:C503,J19,'Expense Tracker'!L4:L503,MONTH(TODAY()),'Expense Tracker'!M4:M503,YEAR(TODAY()))
A20: ='Debt Tracker'!A6 | B20: ='Debt Tracker'!D6 | C20: ='Debt Tracker'!M6 | E20: =IF(N6=0,"🎉 All bills paid!",INDEX('Bills Calendar'!$A$4:$A$18,N6)&" — "&TEXT(INDEX('Bills Calendar'!$H$4:$H$18,N6),"MMM D")) | F20: =IF(N6=0,"",INDEX('Bills Calendar'!$D$4:$D$18,N6)) | G20: =IF(N6=0,"",INDEX('Bills Calendar'!$L$4:$L$18,N6)) | J20: Insurance | K20: =SUMIFS('Expense Tracker'!E4:E503,'Expense Tracker'!C4:C503,J20,'Expense Tracker'!L4:L503,MONTH(TODAY()),'Expense Tracker'!M4:M503,YEAR(TODAY()))
A21: ='Debt Tracker'!A7 | B21: ='Debt Tracker'!D7 | C21: ='Debt Tracker'!M7 | E21: =IF(N7=0,"🎉 All bills paid!",INDEX('Bills Calendar'!$A$4:$A$18,N7)&" — "&TEXT(INDEX('Bills Calendar'!$H$4:$H$18,N7),"MMM D")) | F21: =IF(N7=0,"",INDEX('Bills Calendar'!$D$4:$D$18,N7)) | G21: =IF(N7=0,"",INDEX('Bills Calendar'!$L$4:$L$18,N7)) | J21: Other | K21: =SUMIFS('Expense Tracker'!E4:E503,'Expense Tracker'!C4:C503,J21,'Expense Tracker'!L4:L503,MONTH(TODAY()),'Expense Tracker'!M4:M503,YEAR(TODAY()))
A22: Total Debt | B22: =SUM('Debt Tracker'!D4:D7) | C22: =REPT("█",ROUND((IFERROR((SUM('Debt Tracker'!C4:C7)-SUM('Debt Tracker'!D4:D7))/SUM('Debt Tracker'!C4:C7),0))*20,0))&REPT("░",20-ROUND((IFERROR((SUM('Debt Tracker'!C4:C7)-SUM('Debt Tracker'!D4:D7))/SUM('Debt Tracker'!C4:C7),0))*20,0))&" "&TEXT(IFERROR((SUM('Debt Tracker'!C4:C7)-SUM('Debt Tracker'!D4:D7))/SUM('Debt Tracker'!C4:C7),0),"0%")
A24: 🧾 RECENT EXPENSES
A25: Date | B25: Merchant | D25: Category | F25: Need/Want | G25: Amount
A26: =IF(O4=0,"",INDEX('Expense Tracker'!$A$4:$A$503,O4)) | B26: =IF(O4=0,"",INDEX('Expense Tracker'!$B$4:$B$503,O4)) | D26: =IF(O4=0,"",INDEX('Expense Tracker'!$C$4:$C$503,O4)) | F26: =IF(O4=0,"",INDEX('Expense Tracker'!$G$4:$G$503,O4)) | G26: =IF(O4=0,"",INDEX('Expense Tracker'!$E$4:$E$503,O4))
A27: =IF(O5=0,"",INDEX('Expense Tracker'!$A$4:$A$503,O5)) | B27: =IF(O5=0,"",INDEX('Expense Tracker'!$B$4:$B$503,O5)) | D27: =IF(O5=0,"",INDEX('Expense Tracker'!$C$4:$C$503,O5)) | F27: =IF(O5=0,"",INDEX('Expense Tracker'!$G$4:$G$503,O5)) | G27: =IF(O5=0,"",INDEX('Expense Tracker'!$E$4:$E$503,O5))
A28: =IF(O6=0,"",INDEX('Expense Tracker'!$A$4:$A$503,O6)) | B28: =IF(O6=0,"",INDEX('Expense Tracker'!$B$4:$B$503,O6)) | D28: =IF(O6=0,"",INDEX('Expense Tracker'!$C$4:$C$503,O6)) | F28: =IF(O6=0,"",INDEX('Expense Tracker'!$G$4:$G$503,O6)) | G28: =IF(O6=0,"",INDEX('Expense Tracker'!$E$4:$E$503,O6))
A29: =IF(O7=0,"",INDEX('Expense Tracker'!$A$4:$A$503,O7)) | B29: =IF(O7=0,"",INDEX('Expense Tracker'!$B$4:$B$503,O7)) | D29: =IF(O7=0,"",INDEX('Expense Tracker'!$C$4:$C$503,O7)) | F29: =IF(O7=0,"",INDEX('Expense Tracker'!$G$4:$G$503,O7)) | G29: =IF(O7=0,"",INDEX('Expense Tracker'!$E$4:$E$503,O7))
A30: =IF(O8=0,"",INDEX('Expense Tracker'!$A$4:$A$503,O8)) | B30: =IF(O8=0,"",INDEX('Expense Tracker'!$B$4:$B$503,O8)) | D30: =IF(O8=0,"",INDEX('Expense Tracker'!$C$4:$C$503,O8)) | F30: =IF(O8=0,"",INDEX('Expense Tracker'!$G$4:$G$503,O8)) | G30: =IF(O8=0,"",INDEX('Expense Tracker'!$E$4:$E$503,O8))

Sheet START HERE
A1: 💚 Ultimate Budget Planner
A2: Your complete financial management system
A4: ⚙️ SETUP — Enter Your Info Here (Only Edit Yellow Cells)
A5: Your Name | B5: Alex Johnson | C5: Example: Alex Johnson
A6: Currency Symbol | B6: $ | C6: Example: $
A7: Current Month | B7: =TEXT(TODAY(),"MMMM YYYY") | C7: Auto-fills from today's date
A8: Monthly Income | B8: 5500 | C8: Example: 5500
A9: Monthly Savings Goal % | B9: 0.2 | C9: Example: 0.2
A11: 📖 HOW TO USE THIS PLANNER
A12: 1. | B12: Expense Tracker | D12: Log every expense daily as it happens.
A13: 2. | B13: Monthly Budget | D13: Plan your spending limits for each category.
A14: 3. | B14: Dashboard | D14: Check your progress weekly at a glance.
A15: 4. | B15: Savings Goals | D15: Set and track targets for what matters most.
A16: 5. | B16: Bills Calendar | D16: Track every bill so you never miss a payment.
A17: 6. | B17: Income Tracker | D17: Log all income sources as they arrive.
A18: 7. | B18: Debt Tracker | D18: Plan your debt payoff with avalanche or snowball.
A19: 8. | B19: Annual Overview | D19: Review trends at the end of each month.
A21: 🗺️ SHEET GUIDE
A22: Sheet Name | C22: Purpose | F22: Best Used For | H22: How Often
A23: 📊 Dashboard | C23: Command center with KPIs and progress | F23: Quick status checks | H23: Weekly
A24: 📅 Monthly Budget | C24: Plan and track monthly spending limits | F24: Setting category budgets | H24: Monthly
A25: 📆 Weekly Budget | C25: Break the month into 5 weekly views | F25: Tight week-to-week control | H25: Weekly
A26: 💵 Paycheck Budget | C26: Allocate each paycheck to categories | F26: Paycheck-to-paycheck planning | H26: Per paycheck
A27: 📋 Biweekly Budget | C27: Plan two pay periods per month | F27: Biweekly pay schedules | H27: Biweekly
A28: 💳 Expense Tracker | C28: Log every transaction | F28: Daily expense logging | H28: Daily
A29: 💰 Income Tracker | C29: Log all income sources | F29: Tracking gross/net income | H29: Per income
A30: 🎯 Savings Goals | C30: Track progress toward savings targets | F30: Big purchases & emergency funds | H30: Monthly
A31: 🏦 Debt Tracker | C31: Plan and track debt payoff | F31: Paying down loans & cards | H31: Monthly
A32: 🪣 Sinking Funds | C32: Save monthly for future expenses | F32: Irregular planned costs | H32: Monthly
A33: 📱 Subscriptions | C33: Track recurring subscriptions | F33: Finding what to cancel | H33: Monthly
... A35: 📈 Annual Overview | C35: 12-month financial summary | F35: Year-end review & trends | H35: Monthly
A37: ⚠️ IMPORTANT TIPS
A38: • Only edit cells with a YELLOW background — these are your inputs.
A39: • GREEN and WHITE cells contain formulas — do not delete or overwrite them.
A40: • Start a new copy of this file each month to keep history clean.
A41: • Back up your file to Google Drive weekly.
A43: 📌 GOOGLE SHEETS USERS: Go to File → Import → Upload this file → Replace spreadsheet. Then visit each sheet and add charts using Insert → Chart for a richer view. 📌 EXCEL USERS: Open directly — all formatting and formulas work natively.

Sheet Monthly Budget
A1: 📅 MONTHLY BUDGET PLANNER
A2: Total Budgeted | B2: =SUM(E4:E103) | C2: Total Actual | D2: =SUM(F4:F103) | E2: Total Saved | F2: =B2-D2 | G2: =IF(F2>=0,"✅ Under Budget by "&TEXT(F2,"#,##0.00"),"⚠️ Over Budget by "&TEXT(-F2,"#,##0.00"))
A3: Date | B3: Category | C3: Subcategory | D3: Description | E3: Budgeted | F3: Actual | G3: Difference | H3: % Used | I3: Payment Method | J3: Notes | K3: Running Total
A4: 46174 | B4: Housing | C4: Rent | D4: Monthly rent payment | E4: 1500 | F4: 1500 | G4: =E4-F4 | H4: =IFERROR(F4/E4,0) | I4: Bank Transfer | K4: =SUM($F$4:F4)
A5: 46176 | B5: Food & Dining | C5: Groceries | D5: Weekly grocery run | E5: 500 | F5: 540 | G5: =E5-F5 | H5: =IFERROR(F5/E5,0) | I5: Debit Card | K5: =SUM($F$4:F5)
A6: 46178 | B6: Transportation | C6: Gas | D6: Fuel for car | E6: 150 | F6: 165 | G6: =E6-F6 | H6: =IFERROR(F6/E6,0) | I6: Credit Card | K6: =SUM($F$4:F6)
A7: 46180 | B7: Entertainment | C7: Streaming | D7: Netflix + Spotify | E7: 30 | F7: 30 | G7: =E7-F7 | H7: =IFERROR(F7/E7,0) | I7: Credit Card | K7: =SUM($F$4:F7)
A8: 46182 | B8: Shopping | C8: Clothing | D8: New work clothes | E8: 100 | F8: 85 | G8: =E8-F8 | H8: =IFERROR(F8/E8,0) | I8: Credit Card | K8: =SUM($F$4:F8)
A9: 46184 | B9: Healthcare | C9: Doctor | D9: Annual checkup copay | E9: 50 | F9: 50 | G9: =E9-F9 | H9: =IFERROR(F9/E9,0) | I9: Debit Card | K9: =SUM($F$4:F9)
A10: 46186 | B10: Utilities | C10: Electricity | D10: Power bill | E10: 120 | F10: 135 | G10: =E10-F10 | H10: =IFERROR(F10/E10,0) | I10: Bank Transfer | K10: =SUM($F$4:F10)
A11: 46188 | B11: Education | C11: Courses | D11: Online course | E11: 50 | F11: 0 | G11: =E11-F11 | H11: =IFERROR(F11/E11,0) | I11: Credit Card | J11: Not started yet | K11: =SUM($F$4:F11)
A12: 46190 | B12: Personal Care | C12: Haircuts | D12: Haircut | E12: 40 | F12: 45 | G12: =E12-F12 | H12: =IFERROR(F12/E12,0) | I12: Cash | K12: =SUM($F$4:F12)
A13: 46192 | B13: Savings | C13: General Savings | D13: Emergency fund transfer | E13: 500 | F13: 500 | G13: =E13-F13 | H13: =IFERROR(F13/E13,0) | I13: Bank Transfer | K13: =SUM($F$4:F13)
A14: 46194 | B14: Debt Payment | C14: Credit Card | D14: Minimum payment | E14: 200 | F14: 200 | G14: =E14-F14 | H14: =IFERROR(F14/E14,0) | I14: Bank Transfer | K14: =SUM($F$4:F14)
A15: 46196 | B15: Other | C15: Other | D15: Miscellaneous | E15: 50 | F15: 60 | G15: =E15-F15 | H15: =IFERROR(F15/E15,0) | I15: Cash | J15: Birthday gift | K15: =SUM($F$4:F15)
G16: =E16-F16 | H16: =IFERROR(F16/E16,0) | K16: =SUM($F$4:F16)
G17: =E17-F17 | H17: =IFERROR(F17/E17,0) | K17: =SUM($F$4:F17)
G18: =E18-F18 | H18: =IFERROR(F18/E18,0) | K18: =SUM($F$4:F18)
G19: =E19-F19 | H19: =IFERROR(F19/E19,0) | K19: =SUM($F$4:F19)
G20: =E20-F20 | H20: =IFERROR(F20/E20,0) | K20: =SUM($F$4:F20)
G21: =E21-F21 | H21: =IFERROR(F21/E21,0) | K21: =SUM($F$4:F21)
G22: =E22-F22 | H22: =IFERROR(F22/E22,0) | K22: =SUM($F$4:F22)
G23: =E23-F23 | H23: =IFERROR(F23/E23,0) | K23: =SUM($F$4:F23)
G24: =E24-F24 | H24: =IFERROR(F24/E24,0) | K24: =SUM($F$4:F24)
G25: =E25-F25 | H25: =IFERROR(F25/E25,0) | K25: =SUM($F$4:F25)
G26: =E26-F26 | H26: =IFERROR(F26/E26,0) | K26: =SUM($F$4:F26)
G27: =E27-F27 | H27: =IFERROR(F27/E27,0) | K27: =SUM($F$4:F27)
... G103: =E103-F103 | H103: =IFERROR(F103/E103,0) | K103: =SUM($F$4:F103)

Sheet Weekly Budget
A1: 📆 WEEKLY BUDGET
A2: Category | B2: ="Week 1: "&TEXT(DATE(YEAR(TODAY()),MONTH(TODAY()),1),"MMM D")&"–"&TEXT(DATE(YEAR(TODAY()),MONTH(TODAY()),7),"MMM D") | C2: ="Week 2: "&TEXT(DATE(YEAR(TODAY()),MONTH(TODAY()),8),"MMM D")&"–"&TEXT(DATE(YEAR(TODAY()),MONTH(TODAY()),14),"MMM D") | D2: ="Week 3: "&TEXT(DATE(YEAR(TODAY()),MONTH(TODAY()),15),"MMM D")&"–"&TEXT(DATE(YEAR(TODAY()),MONTH(TODAY()),21),"MMM D") | E2: ="Week 4: "&TEXT(DATE(YEAR(TODAY()),MONTH(TODAY()),22),"MMM D")&"–"&TEXT(DATE(YEAR(TODAY()),MONTH(TODAY()),28),"MMM D") | F2: ="Week 5: "&TEXT(DATE(YEAR(TODAY()),MONTH(TODAY()),29),"MMM D")&"–"&TEXT(DATE(YEAR(TODAY()),MONTH(TODAY()),28),"MMM D") | G2: Monthly Total
A3: Income This Week | B3: 1100 | C3: 1100 | D3: 1100 | E3: 1100 | F3: 1100 | G3: =SUM(B3:F3)
A5: Housing | B5: 0 | C5: 0 | D5: 0 | E5: 0 | F5: 0 | G5: =SUM(B5:F5)
A6: Food & Dining | B6: 0 | C6: 0 | D6: 0 | E6: 0 | F6: 0 | G6: =SUM(B6:F6)
A7: Transportation | B7: 0 | C7: 0 | D7: 0 | E7: 0 | F7: 0 | G7: =SUM(B7:F7)
A8: Entertainment | B8: 0 | C8: 0 | D8: 0 | E8: 0 | F8: 0 | G8: =SUM(B8:F8)
A9: Shopping | B9: 0 | C9: 0 | D9: 0 | E9: 0 | F9: 0 | G9: =SUM(B9:F9)
A10: Utilities | B10: 0 | C10: 0 | D10: 0 | E10: 0 | F10: 0 | G10: =SUM(B10:F10)
A11: Healthcare | B11: 0 | C11: 0 | D11: 0 | E11: 0 | F11: 0 | G11: =SUM(B11:F11)
A12: Personal | B12: 0 | C12: 0 | D12: 0 | E12: 0 | F12: 0 | G12: =SUM(B12:F12)
A13: Savings | B13: 0 | C13: 0 | D13: 0 | E13: 0 | F13: 0 | G13: =SUM(B13:F13)
A14: Other | B14: 0 | C14: 0 | D14: 0 | E14: 0 | F14: 0 | G14: =SUM(B14:F14)
A16: Total Expenses | B16: =SUM(B5:B14) | C16: =SUM(C5:C14) | D16: =SUM(D5:D14) | E16: =SUM(E5:E14) | F16: =SUM(F5:F14) | G16: =SUM(G5:G14)
A17: Net (Income - Expenses) | B17: =B3-B16 | C17: =C3-C16 | D17: =D3-D16 | E17: =E3-E16 | F17: =F3-F16 | G17: =G3-G16
A18: Remaining to Spend | B18: =MAX(B17,0) | C18: =MAX(C17,0) | D18: =MAX(D17,0) | E18: =MAX(E17,0) | F18: =MAX(F17,0) | G18: =MAX(G17,0)
A19: Budget Used | B19: =REPT("█",ROUND((IFERROR(B16/B3,0))*20,0))&REPT("░",20-ROUND((IFERROR(B16/B3,0))*20,0))&" "&TEXT(IFERROR(B16/B3,0),"0%") | C19: =REPT("█",ROUND((IFERROR(C16/C3,0))*20,0))&REPT("░",20-ROUND((IFERROR(C16/C3,0))*20,0))&" "&TEXT(IFERROR(C16/C3,0),"0%") | D19: =REPT("█",ROUND((IFERROR(D16/D3,0))*20,0))&REPT("░",20-ROUND((IFERROR(D16/D3,0))*20,0))&" "&TEXT(IFERROR(D16/D3,0),"0%") | E19: =REPT("█",ROUND((IFERROR(E16/E3,0))*20,0))&REPT("░",20-ROUND((IFERROR(E16/E3,0))*20,0))&" "&TEXT(IFERROR(E16/E3,0),"0%") | F19: =REPT("█",ROUND((IFERROR(F16/F3,0))*20,0))&REPT("░",20-ROUND((IFERROR(F16/F3,0))*20,0))&" "&TEXT(IFERROR(F16/F3,0),"0%") | G19: =REPT("█",ROUND((IFERROR(G16/G3,0))*20,0))&REPT("░",20-ROUND((IFERROR(G16/G3,0))*20,0))&" "&TEXT(IFERROR(G16/G3,0),"0%")

Sheet Paycheck Budget
A1: 💵 PAYCHECK BUDGET
A2: Pay Date | B2: Gross Income | C2: Taxes % | D2: Net Income | E2: Bills | F2: Groceries | G2: Transport | H2: Savings | I2: Investments | J2: Debt Payment | K2: Entertainment | L2: Total Allocated | M2: Remaining | N2: Fully Allocated?
A3: 46187 | B3: 1375 | C3: 0.22 | D3: =B3*(1-C3) | E3: 500 | F3: 150 | G3: 80 | H3: 150 | I3: 50 | J3: 50 | K3: 40 | L3: =SUM(E3:K3) | M3: =D3-L3 | N3: =IF(ROUND(M3,2)=0,"✅",IF(M3>0,"✅ "&TEXT(M3,"#,##0.00")&" left","⚠️ "&TEXT(-M3,"#,##0.00")&" over"))
A4: 46194 | B4: 1375 | C4: 0.22 | D4: =B4*(1-C4) | E4: 500 | F4: 150 | G4: 80 | H4: 150 | I4: 50 | J4: 50 | K4: 40 | L4: =SUM(E4:K4) | M4: =D4-L4 | N4: =IF(ROUND(M4,2)=0,"✅",IF(M4>0,"✅ "&TEXT(M4,"#,##0.00")&" left","⚠️ "&TEXT(-M4,"#,##0.00")&" over"))
A5: 46201 | B5: 1375 | C5: 0.22 | D5: =B5*(1-C5) | E5: 500 | F5: 150 | G5: 80 | H5: 150 | I5: 50 | J5: 50 | K5: 40 | L5: =SUM(E5:K5) | M5: =D5-L5 | N5: =IF(ROUND(M5,2)=0,"✅",IF(M5>0,"✅ "&TEXT(M5,"#,##0.00")&" left","⚠️ "&TEXT(-M5,"#,##0.00")&" over"))
A6: 46208 | B6: 1375 | C6: 0.22 | D6: =B6*(1-C6) | E6: 500 | F6: 150 | G6: 80 | H6: 150 | I6: 50 | J6: 50 | K6: 40 | L6: =SUM(E6:K6) | M6: =D6-L6 | N6: =IF(ROUND(M6,2)=0,"✅",IF(M6>0,"✅ "&TEXT(M6,"#,##0.00")&" left","⚠️ "&TEXT(-M6,"#,##0.00")&" over"))
A7: 46215 | B7: 1375 | C7: 0.22 | D7: =B7*(1-C7) | E7: 500 | F7: 150 | G7: 80 | H7: 150 | I7: 50 | J7: 50 | K7: 40 | L7: =SUM(E7:K7) | M7: =D7-L7 | N7: =IF(ROUND(M7,2)=0,"✅",IF(M7>0,"✅ "&TEXT(M7,"#,##0.00")&" left","⚠️ "&TEXT(-M7,"#,##0.00")&" over"))
A8: 46222 | B8: 1375 | C8: 0.22 | D8: =B8*(1-C8) | E8: 500 | F8: 150 | G8: 80 | H8: 150 | I8: 50 | J8: 50 | K8: 40 | L8: =SUM(E8:K8) | M8: =D8-L8 | N8: =IF(ROUND(M8,2)=0,"✅",IF(M8>0,"✅ "&TEXT(M8,"#,##0.00")&" left","⚠️ "&TEXT(-M8,"#,##0.00")&" over"))
A9: 46229 | B9: 1375 | C9: 0.22 | D9: =B9*(1-C9) | E9: 500 | F9: 150 | G9: 80 | H9: 150 | I9: 50 | J9: 50 | K9: 40 | L9: =SUM(E9:K9) | M9: =D9-L9 | N9: =IF(ROUND(M9,2)=0,"✅",IF(M9>0,"✅ "&TEXT(M9,"#,##0.00")&" left","⚠️ "&TEXT(-M9,"#,##0.00")&" over"))
A10: 46236 | B10: 1375 | C10: 0.22 | D10: =B10*(1-C10) | E10: 500 | F10: 150 | G10: 80 | H10: 150 | I10: 50 | J10: 50 | K10: 40 | L10: =SUM(E10:K10) | M10: =D10-L10 | N10: =IF(ROUND(M10,2)=0,"✅",IF(M10>0,"✅ "&TEXT(M10,"#,##0.00")&" left","⚠️ "&TEXT(-M10,"#,##0.00")&" over"))
A11: 46243 | B11: 1375 | C11: 0.22 | D11: =B11*(1-C11) | E11: 500 | F11: 150 | G11: 80 | H11: 150 | I11: 50 | J11: 50 | K11: 40 | L11: =SUM(E11:K11) | M11: =D11-L11 | N11: =IF(ROUND(M11,2)=0,"✅",IF(M11>0,"✅ "&TEXT(M11,"#,##0.00")&" left","⚠️ "&TEXT(-M11,"#,##0.00")&" over"))
A12: 46250 | B12: 1375 | C12: 0.22 | D12: =B12*(1-C12) | E12: 500 | F12: 150 | G12: 80 | H12: 150 | I12: 50 | J12: 50 | K12: 40 | L12: =SUM(E12:K12) | M12: =D12-L12 | N12: =IF(ROUND(M12,2)=0,"✅",IF(M12>0,"✅ "&TEXT(M12,"#,##0.00")&" left","⚠️ "&TEXT(-M12,"#,##0.00")&" over"))
A13: 46257 | B13: 1375 | C13: 0.22 | D13: =B13*(1-C13) | E13: 500 | F13: 150 | G13: 80 | H13: 150 | I13: 50 | J13: 50 | K13: 40 | L13: =SUM(E13:K13) | M13: =D13-L13 | N13: =IF(ROUND(M13,2)=0,"✅",IF(M13>0,"✅ "&TEXT(M13,"#,##0.00")&" left","⚠️ "&TEXT(-M13,"#,##0.00")&" over"))
A14: 46264 | B14: 1375 | C14: 0.22 | D14: =B14*(1-C14) | E14: 500 | F14: 150 | G14: 80 | H14: 150 | I14: 50 | J14: 50 | K14: 40 | L14: =SUM(E14:K14) | M14: =D14-L14 | N14: =IF(ROUND(M14,2)=0,"✅",IF(M14>0,"✅ "&TEXT(M14,"#,##0.00")&" left","⚠️ "&TEXT(-M14,"#,##0.00")&" over"))
A16: Totals | B16: =SUM(B3:B14) | D16: =SUM(D3:D14) | E16: =SUM(E3:E14) | F16: =SUM(F3:F14) | G16: =SUM(G3:G14) | H16: =SUM(H3:H14) | I16: =SUM(I3:I14) | J16: =SUM(J3:J14) | K16: =SUM(K3:K14) | ... M16: =SUM(M3:M14)
A17: Average per Paycheck | B17: =AVERAGE(B3:B14) | D17: =AVERAGE(D3:D14) | E17: =AVERAGE(E3:E14) | F17: =AVERAGE(F3:F14) | G17: =AVERAGE(G3:G14) | H17: =AVERAGE(H3:H14) | I17: =AVERAGE(I3:I14) | J17: =AVERAGE(J3:J14) | K17: =AVERAGE(K3:K14) | ... M17: =AVERAGE(M3:M14)
A18: Savings Rate | B18: =(H16+I16)/D16
A20: 📐 50/30/20 ALLOCATION CHECK
A21: Allocation Group | E21: Your % | F21: Target % | G21: Status
A22: Needs (Bills, Groceries, Transport) | E22: =(E16+F16+G16)/D16 | F22: 0.5 | G22: =IF(E22<=F22*1.1,"✅ On Track","⚠️ Above Target")
A23: Wants (Entertainment) | E23: =K16/D16 | F23: 0.3 | G23: =IF(E23<=F23*1.1,"✅ On Track","⚠️ Above Target")
A24: Savings & Debt (Savings, Investments, Debt) | E24: =(H16+I16+J16)/D16 | F24: 0.2 | G24: =IF(E24<=F24*1.1,"✅ On Track","⚠️ Above Target")

Sheet Biweekly Budget
A1: 📋 BIWEEKLY BUDGET
A2: Category | B2: PAYCHECK 1 (1st–15th) | C2: PAYCHECK 2 (16th–End) | D2: Monthly Total
A3: Net Income (Paycheck) | B3: 1900 | C3: 1900 | D3: =B3+C3
A4: Rollover from Previous Period | B4: 0 | C4: =B13 | D4: —
A5: Available Funds | B5: =B3+B4 | C5: =C3+C4 | D5: =B5+C5
A6: 💸 EXPENSES
A7: Fixed Bills (Rent, Insurance, Subscriptions) | B7: 1500 | C7: 200 | D7: =B7+C7
A8: Variable Expenses (Food, Gas, Entertainment) | B8: 350 | C8: 350 | D8: =B8+C8
A9: Savings | B9: 150 | C9: 150 | D9: =B9+C9
A10: Investments | B10: 50 | C10: 50 | D10: =B10+C10
A11: Debt Payments | B11: 100 | C11: 100 | D11: =B11+C11
A12: Total Expenses | B12: =SUM(B7:B11) | C12: =SUM(C7:C11) | D12: =SUM(D7:D11)
A13: Remaining Balance | B13: =B5-B12 | C13: =C5-C12 | D13: =C13
A15: 💡 Any leftover (or shortfall) from Paycheck 1 automatically rolls into Paycheck 2's available funds, so you always see a true running balance.

Sheet Expense Tracker
A1: 💳 EXPENSE TRACKER
A2: Total Spent | B2: =SUM(E4:E503) | C2: Needs Total | D2: =SUMIF(G4:G503,"Need",E4:E503) | E2: Wants Total | F2: =SUMIF(G4:G503,"Want",E4:E503) | G2: Largest Purchase | H2: =MAX(E4:E503) | I2: Transactions | J2: =COUNTA(B4:B503)
A3: Date | B3: Merchant | C3: Category | D3: Subcategory | E3: Amount | F3: Payment Method | G3: Need or Want | H3: Recurring? | I3: Notes | J3: Month | K3: Week# | L3: Month# | M3: Year
A4: 46174 | B4: Whole Foods | C4: Food & Dining | D4: Groceries | E4: 125.4 | F4: Debit Card | G4: Need | H4: No | J4: =IF(A4="","",TEXT(A4,"MMMM YYYY")) | K4: =IF(A4="","",WEEKNUM(A4)) | L4: =IF(A4="","",MONTH(A4)) | M4: =IF(A4="","",YEAR(A4))
A5: 46175 | B5: Amazon | C5: Shopping | D5: Electronics | E5: 89.99 | F5: Credit Card | G5: Want | H5: No | J5: =IF(A5="","",TEXT(A5,"MMMM YYYY")) | K5: =IF(A5="","",WEEKNUM(A5)) | L5: =IF(A5="","",MONTH(A5)) | M5: =IF(A5="","",YEAR(A5))
A6: 46175 | B6: Shell Gas | C6: Transportation | D6: Gas | E6: 52.3 | F6: Credit Card | G6: Need | H6: No | J6: =IF(A6="","",TEXT(A6,"MMMM YYYY")) | K6: =IF(A6="","",WEEKNUM(A6)) | L6: =IF(A6="","",MONTH(A6)) | M6: =IF(A6="","",YEAR(A6))
A7: 46176 | B7: Netflix | C7: Entertainment | D7: Streaming | E7: 15.49 | F7: Credit Card | G7: Want | H7: Yes | J7: =IF(A7="","",TEXT(A7,"MMMM YYYY")) | K7: =IF(A7="","",WEEKNUM(A7)) | L7: =IF(A7="","",MONTH(A7)) | M7: =IF(A7="","",YEAR(A7))
A8: 46176 | B8: Spotify | C8: Entertainment | D8: Streaming | E8: 11.99 | F8: Credit Card | G8: Want | H8: Yes | J8: =IF(A8="","",TEXT(A8,"MMMM YYYY")) | K8: =IF(A8="","",WEEKNUM(A8)) | L8: =IF(A8="","",MONTH(A8)) | M8: =IF(A8="","",YEAR(A8))
A9: 46177 | B9: Target | C9: Shopping | D9: Clothing | E9: 64.2 | F9: Debit Card | G9: Want | H9: No | J9: =IF(A9="","",TEXT(A9,"MMMM YYYY")) | K9: =IF(A9="","",WEEKNUM(A9)) | L9: =IF(A9="","",MONTH(A9)) | M9: =IF(A9="","",YEAR(A9))
A10: 46178 | B10: CVS Pharmacy | C10: Healthcare | D10: Pharmacy | E10: 23.75 | F10: Debit Card | G10: Need | H10: No | J10: =IF(A10="","",TEXT(A10,"MMMM YYYY")) | K10: =IF(A10="","",WEEKNUM(A10)) | L10: =IF(A10="","",MONTH(A10)) | M10: =IF(A10="","",YEAR(A10))
A11: 46179 | B11: Uber | C11: Transportation | D11: Public Transit | E11: 18.5 | F11: Credit Card | G11: Want | H11: No | J11: =IF(A11="","",TEXT(A11,"MMMM YYYY")) | K11: =IF(A11="","",WEEKNUM(A11)) | L11: =IF(A11="","",MONTH(A11)) | M11: =IF(A11="","",YEAR(A11))
A12: 46180 | B12: Chipotle | C12: Food & Dining | D12: Restaurants | E12: 13.85 | F12: Cash | G12: Want | H12: No | J12: =IF(A12="","",TEXT(A12,"MMMM YYYY")) | K12: =IF(A12="","",WEEKNUM(A12)) | L12: =IF(A12="","",MONTH(A12)) | M12: =IF(A12="","",YEAR(A12))
A13: 46180 | B13: Starbucks | C13: Food & Dining | D13: Coffee | E13: 6.45 | F13: Debit Card | G13: Want | H13: No | I13: Daily habit | J13: =IF(A13="","",TEXT(A13,"MMMM YYYY")) | K13: =IF(A13="","",WEEKNUM(A13)) | L13: =IF(A13="","",MONTH(A13)) | M13: =IF(A13="","",YEAR(A13))
A14: 46181 | B14: Planet Fitness | C14: Personal Care | D14: Gym | E14: 29.99 | F14: Bank Transfer | G14: Need | H14: Yes | J14: =IF(A14="","",TEXT(A14,"MMMM YYYY")) | K14: =IF(A14="","",WEEKNUM(A14)) | L14: =IF(A14="","",MONTH(A14)) | M14: =IF(A14="","",YEAR(A14))
A15: 46182 | B15: Apple | C15: Shopping | D15: Electronics | E15: 249 | F15: Credit Card | G15: Want | H15: No | I15: New earbuds | J15: =IF(A15="","",TEXT(A15,"MMMM YYYY")) | K15: =IF(A15="","",WEEKNUM(A15)) | L15: =IF(A15="","",MONTH(A15)) | M15: =IF(A15="","",YEAR(A15))
A16: 46183 | B16: Whole Foods | C16: Food & Dining | D16: Groceries | E16: 142.1 | F16: Debit Card | G16: Need | H16: No | J16: =IF(A16="","",TEXT(A16,"MMMM YYYY")) | K16: =IF(A16="","",WEEKNUM(A16)) | L16: =IF(A16="","",MONTH(A16)) | M16: =IF(A16="","",YEAR(A16))
A17: 46184 | B17: Shell Gas | C17: Transportation | D17: Gas | E17: 48.75 | F17: Credit Card | G17: Need | H17: No | J17: =IF(A17="","",TEXT(A17,"MMMM YYYY")) | K17: =IF(A17="","",WEEKNUM(A17)) | L17: =IF(A17="","",MONTH(A17)) | M17: =IF(A17="","",YEAR(A17))
A18: 46185 | B18: Electric Co. | C18: Utilities | D18: Electricity | E18: 135 | F18: Bank Transfer | G18: Need | H18: Yes | J18: =IF(A18="","",TEXT(A18,"MMMM YYYY")) | K18: =IF(A18="","",WEEKNUM(A18)) | L18: =IF(A18="","",MONTH(A18)) | M18: =IF(A18="","",YEAR(A18))
A19: 46185 | B19: Verizon | C19: Utilities | D19: Phone | E19: 85 | F19: Bank Transfer | G19: Need | H19: Yes | J19: =IF(A19="","",TEXT(A19,"MMMM YYYY")) | K19: =IF(A19="","",WEEKNUM(A19)) | L19: =IF(A19="","",MONTH(A19)) | M19: =IF(A19="","",YEAR(A19))
A20: 46186 | B20: Amazon | C20: Shopping | D20: Other | E20: 34.99 | F20: Credit Card | G20: Want | H20: No | I20: Phone case | J20: =IF(A20="","",TEXT(A20,"MMMM YYYY")) | K20: =IF(A20="","",WEEKNUM(A20)) | L20: =IF(A20="","",MONTH(A20)) | M20: =IF(A20="","",YEAR(A20))
J21: =IF(A21="","",TEXT(A21,"MMMM YYYY")) | K21: =IF(A21="","",WEEKNUM(A21)) | L21: =IF(A21="","",MONTH(A21)) | M21: =IF(A21="","",YEAR(A21))
J22: =IF(A22="","",TEXT(A22,"MMMM YYYY")) | K22: =IF(A22="","",WEEKNUM(A22)) | L22: =IF(A22="","",MONTH(A22)) | M22: =IF(A22="","",YEAR(A22))
J23: =IF(A23="","",TEXT(A23,"MMMM YYYY")) | K23: =IF(A23="","",WEEKNUM(A23)) | L23: =IF(A23="","",MONTH(A23)) | M23: =IF(A23="","",YEAR(A23))
J24: =IF(A24="","",TEXT(A24,"MMMM YYYY")) | K24: =IF(A24="","",WEEKNUM(A24)) | L24: =IF(A24="","",MONTH(A24)) | M24: =IF(A24="","",YEAR(A24))
J25: =IF(A25="","",TEXT(A25,"MMMM YYYY")) | K25: =IF(A25="","",WEEKNUM(A25)) | L25: =IF(A25="","",MONTH(A25)) | M25: =IF(A25="","",YEAR(A25))
J26: =IF(A26="","",TEXT(A26,"MMMM YYYY")) | K26: =IF(A26="","",WEEKNUM(A26)) | L26: =IF(A26="","",MONTH(A26)) | M26: =IF(A26="","",YEAR(A26))
J27: =IF(A27="","",TEXT(A27,"MMMM YYYY")) | K27: =IF(A27="","",WEEKNUM(A27)) | L27: =IF(A27="","",MONTH(A27)) | M27: =IF(A27="","",YEAR(A27))
J28: =IF(A28="","",TEXT(A28,"MMMM YYYY")) | K28: =IF(A28="","",WEEKNUM(A28)) | L28: =IF(A28="","",MONTH(A28)) | M28: =IF(A28="","",YEAR(A28))
J29: =IF(A29="","",TEXT(A29,"MMMM YYYY")) | K29: =IF(A29="","",WEEKNUM(A29)) | L29: =IF(A29="","",MONTH(A29)) | M29: =IF(A29="","",YEAR(A29))
J30: =IF(A30="","",TEXT(A30,"MMMM YYYY")) | K30: =IF(A30="","",WEEKNUM(A30)) | L30: =IF(A30="","",MONTH(A30)) | M30: =IF(A30="","",YEAR(A30))
J31: =IF(A31="","",TEXT(A31,"MMMM YYYY")) | K31: =IF(A31="","",WEEKNUM(A31)) | L31: =IF(A31="","",MONTH(A31)) | M31: =IF(A31="","",YEAR(A31))
J32: =IF(A32="","",TEXT(A32,"MMMM YYYY")) | K32: =IF(A32="","",WEEKNUM(A32)) | L32: =IF(A32="","",MONTH(A32)) | M32: =IF(A32="","",YEAR(A32))
... J503: =IF(A503="","",TEXT(A503,"MMMM YYYY")) | K503: =IF(A503="","",WEEKNUM(A503)) | L503: =IF(A503="","",MONTH(A503)) | M503: =IF(A503="","",YEAR(A503))
A506: 📊 CATEGORY SUMMARY | G506: 🏆 TOP 5 EXPENSES
A507: Category | B507: Total Spent | C507: # Transactions | D507: Avg Transaction | E507: % of Total | G507: Rank | H507: Merchant | I507: Category | J507: Amount
A508: Housing | B508: =SUMIF(C4:C503,A508,E4:E503) | C508: =COUNTIF(C4:C503,A508) | D508: =IFERROR(B508/C508,0) | E508: =IFERROR(B508/SUM(E4:E503),0) | G508: 1 | H508: =IFERROR(INDEX($B$4:$B$503,MATCH(J508,$E$4:$E$503,0)),"") | I508: =IFERROR(INDEX($C$4:$C$503,MATCH(J508,$E$4:$E$503,0)),"") | J508: =LARGE($E$4:$E$503,1)
A509: Food & Dining | B509: =SUMIF(C4:C503,A509,E4:E503) | C509: =COUNTIF(C4:C503,A509) | D509: =IFERROR(B509/C509,0) | E509: =IFERROR(B509/SUM(E4:E503),0) | G509: 2 | H509: =IFERROR(INDEX($B$4:$B$503,MATCH(J509,$E$4:$E$503,0)),"") | I509: =IFERROR(INDEX($C$4:$C$503,MATCH(J509,$E$4:$E$503,0)),"") | J509: =LARGE($E$4:$E$503,2)
A510: Transportation | B510: =SUMIF(C4:C503,A510,E4:E503) | C510: =COUNTIF(C4:C503,A510) | D510: =IFERROR(B510/C510,0) | E510: =IFERROR(B510/SUM(E4:E503),0) | G510: 3 | H510: =IFERROR(INDEX($B$4:$B$503,MATCH(J510,$E$4:$E$503,0)),"") | I510: =IFERROR(INDEX($C$4:$C$503,MATCH(J510,$E$4:$E$503,0)),"") | J510: =LARGE($E$4:$E$503,3)
A511: Entertainment | B511: =SUMIF(C4:C503,A511,E4:E503) | C511: =COUNTIF(C4:C503,A511) | D511: =IFERROR(B511/C511,0) | E511: =IFERROR(B511/SUM(E4:E503),0) | G511: 4 | H511: =IFERROR(INDEX($B$4:$B$503,MATCH(J511,$E$4:$E$503,0)),"") | I511: =IFERROR(INDEX($C$4:$C$503,MATCH(J511,$E$4:$E$503,0)),"") | J511: =LARGE($E$4:$E$503,4)
A512: Shopping | B512: =SUMIF(C4:C503,A512,E4:E503) | C512: =COUNTIF(C4:C503,A512) | D512: =IFERROR(B512/C512,0) | E512: =IFERROR(B512/SUM(E4:E503),0) | G512: 5 | H512: =IFERROR(INDEX($B$4:$B$503,MATCH(J512,$E$4:$E$503,0)),"") | I512: =IFERROR(INDEX($C$4:$C$503,MATCH(J512,$E$4:$E$503,0)),"") | J512: =LARGE($E$4:$E$503,5)
A513: Healthcare | B513: =SUMIF(C4:C503,A513,E4:E503) | C513: =COUNTIF(C4:C503,A513) | D513: =IFERROR(B513/C513,0) | E513: =IFERROR(B513/SUM(E4:E503),0)
A514: Utilities | B514: =SUMIF(C4:C503,A514,E4:E503) | C514: =COUNTIF(C4:C503,A514) | D514: =IFERROR(B514/C514,0) | E514: =IFERROR(B514/SUM(E4:E503),0)
A515: Education | B515: =SUMIF(C4:C503,A515,E4:E503) | C515: =COUNTIF(C4:C503,A515) | D515: =IFERROR(B515/C515,0) | E515: =IFERROR(B515/SUM(E4:E503),0)
A516: Personal Care | B516: =SUMIF(C4:C503,A516,E4:E503) | C516: =COUNTIF(C4:C503,A516) | D516: =IFERROR(B516/C516,0) | E516: =IFERROR(B516/SUM(E4:E503),0)
A517: Savings | B517: =SUMIF(C4:C503,A517,E4:E503) | C517: =COUNTIF(C4:C503,A517) | D517: =IFERROR(B517/C517,0) | E517: =IFERROR(B517/SUM(E4:E503),0)
A518: Investments | B518: =SUMIF(C4:C503,A518,E4:E503) | C518: =COUNTIF(C4:C503,A518) | D518: =IFERROR(B518/C518,0) | E518: =IFERROR(B518/SUM(E4:E503),0)
A519: Debt Payment | B519: =SUMIF(C4:C503,A519,E4:E503) | C519: =COUNTIF(C4:C503,A519) | D519: =IFERROR(B519/C519,0) | E519: =IFERROR(B519/SUM(E4:E503),0)
A520: Kids | B520: =SUMIF(C4:C503,A520,E4:E503) | C520: =COUNTIF(C4:C503,A520) | D520: =IFERROR(B520/C520,0) | E520: =IFERROR(B520/SUM(E4:E503),0)
A521: Pets | B521: =SUMIF(C4:C503,A521,E4:E503) | C521: =COUNTIF(C4:C503,A521) | D521: =IFERROR(B521/C521,0) | E521: =IFERROR(B521/SUM(E4:E503),0)
A522: Travel | B522: =SUMIF(C4:C503,A522,E4:E503) | C522: =COUNTIF(C4:C503,A522) | D522: =IFERROR(B522/C522,0) | E522: =IFERROR(B522/SUM(E4:E503),0)
A523: Subscriptions | B523: =SUMIF(C4:C503,A523,E4:E503) | C523: =COUNTIF(C4:C503,A523) | D523: =IFERROR(B523/C523,0) | E523: =IFERROR(B523/SUM(E4:E503),0)
A524: Insurance | B524: =SUMIF(C4:C503,A524,E4:E503) | C524: =COUNTIF(C4:C503,A524) | D524: =IFERROR(B524/C524,0) | E524: =IFERROR(B524/SUM(E4:E503),0)
A525: Other | B525: =SUMIF(C4:C503,A525,E4:E503) | C525: =COUNTIF(C4:C503,A525) | D525: =IFERROR(B525/C525,0) | E525: =IFERROR(B525/SUM(E4:E503),0)

Sheet Income Tracker
A1: 💰 INCOME TRACKER
A2: Total Gross | B2: =SUM(D4:D103) | C2: Tax Reserved | D2: =SUM(F4:F103) | E2: Total Net | F2: =SUM(G4:G103) | G2: Avg per Entry | H2: =IFERROR(AVERAGE(D4:D103),0)
A3: Date | B3: Source | C3: Description | D3: Amount | E3: Tax Rate % | F3: Tax Reserve | G3: Net After Tax | H3: Month | I3: Category Type | J3: Month# | K3: Year
A4: 46023 | B4: Salary | C4: Biweekly paycheck | D4: 2750 | E4: 0.22 | F4: =D4*E4 | G4: =D4-F4 | H4: =IF(A4="","",TEXT(A4,"MMMM YYYY")) | I4: Active | J4: =IF(A4="","",MONTH(A4)) | K4: =IF(A4="","",YEAR(A4))
A5: 46037 | B5: Salary | C5: Biweekly paycheck | D5: 2750 | E5: 0.22 | F5: =D5*E5 | G5: =D5-F5 | H5: =IF(A5="","",TEXT(A5,"MMMM YYYY")) | I5: Active | J5: =IF(A5="","",MONTH(A5)) | K5: =IF(A5="","",YEAR(A5))
A6: 46054 | B6: Salary | C6: Biweekly paycheck | D6: 2750 | E6: 0.22 | F6: =D6*E6 | G6: =D6-F6 | H6: =IF(A6="","",TEXT(A6,"MMMM YYYY")) | I6: Active | J6: =IF(A6="","",MONTH(A6)) | K6: =IF(A6="","",YEAR(A6))
A7: 46068 | B7: Salary | C7: Biweekly paycheck | D7: 2750 | E7: 0.22 | F7: =D7*E7 | G7: =D7-F7 | H7: =IF(A7="","",TEXT(A7,"MMMM YYYY")) | I7: Active | J7: =IF(A7="","",MONTH(A7)) | K7: =IF(A7="","",YEAR(A7))
A8: 46082 | B8: Salary | C8: Biweekly paycheck | D8: 2750 | E8: 0.22 | F8: =D8*E8 | G8: =D8-F8 | H8: =IF(A8="","",TEXT(A8,"MMMM YYYY")) | I8: Active | J8: =IF(A8="","",MONTH(A8)) | K8: =IF(A8="","",YEAR(A8))
A9: 46096 | B9: Salary | C9: Biweekly paycheck | D9: 2750 | E9: 0.22 | F9: =D9*E9 | G9: =D9-F9 | H9: =IF(A9="","",TEXT(A9,"MMMM YYYY")) | I9: Active | J9: =IF(A9="","",MONTH(A9)) | K9: =IF(A9="","",YEAR(A9))
A10: 46113 | B10: Salary | C10: Biweekly paycheck | D10: 2750 | E10: 0.22 | F10: =D10*E10 | G10: =D10-F10 | H10: =IF(A10="","",TEXT(A10,"MMMM YYYY")) | I10: Active | J10: =IF(A10="","",MONTH(A10)) | K10: =IF(A10="","",YEAR(A10))
A11: 46127 | B11: Salary | C11: Biweekly paycheck | D11: 2750 | E11: 0.22 | F11: =D11*E11 | G11: =D11-F11 | H11: =IF(A11="","",TEXT(A11,"MMMM YYYY")) | I11: Active | J11: =IF(A11="","",MONTH(A11)) | K11: =IF(A11="","",YEAR(A11))
A12: 46143 | B12: Salary | C12: Biweekly paycheck | D12: 2750 | E12: 0.22 | F12: =D12*E12 | G12: =D12-F12 | H12: =IF(A12="","",TEXT(A12,"MMMM YYYY")) | I12: Active | J12: =IF(A12="","",MONTH(A12)) | K12: =IF(A12="","",YEAR(A12))
A13: 46157 | B13: Salary | C13: Biweekly paycheck | D13: 2750 | E13: 0.22 | F13: =D13*E13 | G13: =D13-F13 | H13: =IF(A13="","",TEXT(A13,"MMMM YYYY")) | I13: Active | J13: =IF(A13="","",MONTH(A13)) | K13: =IF(A13="","",YEAR(A13))
A14: 46174 | B14: Salary | C14: Biweekly paycheck | D14: 2750 | E14: 0.22 | F14: =D14*E14 | G14: =D14-F14 | H14: =IF(A14="","",TEXT(A14,"MMMM YYYY")) | I14: Active | J14: =IF(A14="","",MONTH(A14)) | K14: =IF(A14="","",YEAR(A14))
A15: 46188 | B15: Salary | C15: Biweekly paycheck | D15: 2750 | E15: 0.22 | F15: =D15*E15 | G15: =D15-F15 | H15: =IF(A15="","",TEXT(A15,"MMMM YYYY")) | I15: Active | J15: =IF(A15="","",MONTH(A15)) | K15: =IF(A15="","",YEAR(A15))
... A17: 46137 | B17: Dividends | C17: Investment dividend payout | D17: 45 | E17: 0.15 | F17: =D17*E17 | G17: =D17-F17 | H17: =IF(A17="","",TEXT(A17,"MMMM YYYY")) | I17: Passive | J17: =IF(A17="","",MONTH(A17)) | K17: =IF(A17="","",YEAR(A17))
F18: =D18*E18 | G18: =D18-F18 | H18: =IF(A18="","",TEXT(A18,"MMMM YYYY")) | J18: =IF(A18="","",MONTH(A18)) | K18: =IF(A18="","",YEAR(A18))
F19: =D19*E19 | G19: =D19-F19 | H19: =IF(A19="","",TEXT(A19,"MMMM YYYY")) | J19: =IF(A19="","",MONTH(A19)) | K19: =IF(A19="","",YEAR(A19))
F20: =D20*E20 | G20: =D20-F20 | H20: =IF(A20="","",TEXT(A20,"MMMM YYYY")) | J20: =IF(A20="","",MONTH(A20)) | K20: =IF(A20="","",YEAR(A20))
F21: =D21*E21 | G21: =D21-F21 | H21: =IF(A21="","",TEXT(A21,"MMMM YYYY")) | J21: =IF(A21="","",MONTH(A21)) | K21: =IF(A21="","",YEAR(A21))
F22: =D22*E22 | G22: =D22-F22 | H22: =IF(A22="","",TEXT(A22,"MMMM YYYY")) | J22: =IF(A22="","",MONTH(A22)) | K22: =IF(A22="","",YEAR(A22))
F23: =D23*E23 | G23: =D23-F23 | H23: =IF(A23="","",TEXT(A23,"MMMM YYYY")) | J23: =IF(A23="","",MONTH(A23)) | K23: =IF(A23="","",YEAR(A23))
F24: =D24*E24 | G24: =D24-F24 | H24: =IF(A24="","",TEXT(A24,"MMMM YYYY")) | J24: =IF(A24="","",MONTH(A24)) | K24: =IF(A24="","",YEAR(A24))
F25: =D25*E25 | G25: =D25-F25 | H25: =IF(A25="","",TEXT(A25,"MMMM YYYY")) | J25: =IF(A25="","",MONTH(A25)) | K25: =IF(A25="","",YEAR(A25))
F26: =D26*E26 | G26: =D26-F26 | H26: =IF(A26="","",TEXT(A26,"MMMM YYYY")) | J26: =IF(A26="","",MONTH(A26)) | K26: =IF(A26="","",YEAR(A26))
F27: =D27*E27 | G27: =D27-F27 | H27: =IF(A27="","",TEXT(A27,"MMMM YYYY")) | J27: =IF(A27="","",MONTH(A27)) | K27: =IF(A27="","",YEAR(A27))
F28: =D28*E28 | G28: =D28-F28 | H28: =IF(A28="","",TEXT(A28,"MMMM YYYY")) | J28: =IF(A28="","",MONTH(A28)) | K28: =IF(A28="","",YEAR(A28))
F29: =D29*E29 | G29: =D29-F29 | H29: =IF(A29="","",TEXT(A29,"MMMM YYYY")) | J29: =IF(A29="","",MONTH(A29)) | K29: =IF(A29="","",YEAR(A29))
... F103: =D103*E103 | G103: =D103-F103 | H103: =IF(A103="","",TEXT(A103,"MMMM YYYY")) | J103: =IF(A103="","",MONTH(A103)) | K103: =IF(A103="","",YEAR(A103))
A106: 📅 MONTHLY SUMMARY
A107: Month | B107: Gross Income | C107: Tax Reserve | D107: Net Income | E107: # Sources
A108: January | B108: =SUMIFS(D4:D103,J4:J103,1,K4:K103,YEAR(TODAY())) | C108: =SUMIFS(F4:F103,J4:J103,1,K4:K103,YEAR(TODAY())) | D108: =B108-C108 | E108: =COUNTIFS(J4:J103,1,K4:K103,YEAR(TODAY()))
A109: February | B109: =SUMIFS(D4:D103,J4:J103,2,K4:K103,YEAR(TODAY())) | C109: =SUMIFS(F4:F103,J4:J103,2,K4:K103,YEAR(TODAY())) | D109: =B109-C109 | E109: =COUNTIFS(J4:J103,2,K4:K103,YEAR(TODAY()))
A110: March | B110: =SUMIFS(D4:D103,J4:J103,3,K4:K103,YEAR(TODAY())) | C110: =SUMIFS(F4:F103,J4:J103,3,K4:K103,YEAR(TODAY())) | D110: =B110-C110 | E110: =COUNTIFS(J4:J103,3,K4:K103,YEAR(TODAY()))
A111: April | B111: =SUMIFS(D4:D103,J4:J103,4,K4:K103,YEAR(TODAY())) | C111: =SUMIFS(F4:F103,J4:J103,4,K4:K103,YEAR(TODAY())) | D111: =B111-C111 | E111: =COUNTIFS(J4:J103,4,K4:K103,YEAR(TODAY()))
A112: May | B112: =SUMIFS(D4:D103,J4:J103,5,K4:K103,YEAR(TODAY())) | C112: =SUMIFS(F4:F103,J4:J103,5,K4:K103,YEAR(TODAY())) | D112: =B112-C112 | E112: =COUNTIFS(J4:J103,5,K4:K103,YEAR(TODAY()))
A113: June | B113: =SUMIFS(D4:D103,J4:J103,6,K4:K103,YEAR(TODAY())) | C113: =SUMIFS(F4:F103,J4:J103,6,K4:K103,YEAR(TODAY())) | D113: =B113-C113 | E113: =COUNTIFS(J4:J103,6,K4:K103,YEAR(TODAY()))
A114: July | B114: =SUMIFS(D4:D103,J4:J103,7,K4:K103,YEAR(TODAY())) | C114: =SUMIFS(F4:F103,J4:J103,7,K4:K103,YEAR(TODAY())) | D114: =B114-C114 | E114: =COUNTIFS(J4:J103,7,K4:K103,YEAR(TODAY()))
A115: August | B115: =SUMIFS(D4:D103,J4:J103,8,K4:K103,YEAR(TODAY())) | C115: =SUMIFS(F4:F103,J4:J103,8,K4:K103,YEAR(TODAY())) | D115: =B115-C115 | E115: =COUNTIFS(J4:J103,8,K4:K103,YEAR(TODAY()))
A116: September | B116: =SUMIFS(D4:D103,J4:J103,9,K4:K103,YEAR(TODAY())) | C116: =SUMIFS(F4:F103,J4:J103,9,K4:K103,YEAR(TODAY())) | D116: =B116-C116 | E116: =COUNTIFS(J4:J103,9,K4:K103,YEAR(TODAY()))
A117: October | B117: =SUMIFS(D4:D103,J4:J103,10,K4:K103,YEAR(TODAY())) | C117: =SUMIFS(F4:F103,J4:J103,10,K4:K103,YEAR(TODAY())) | D117: =B117-C117 | E117: =COUNTIFS(J4:J103,10,K4:K103,YEAR(TODAY()))
A118: November | B118: =SUMIFS(D4:D103,J4:J103,11,K4:K103,YEAR(TODAY())) | C118: =SUMIFS(F4:F103,J4:J103,11,K4:K103,YEAR(TODAY())) | D118: =B118-C118 | E118: =COUNTIFS(J4:J103,11,K4:K103,YEAR(TODAY()))
A119: December | B119: =SUMIFS(D4:D103,J4:J103,12,K4:K103,YEAR(TODAY())) | C119: =SUMIFS(F4:F103,J4:J103,12,K4:K103,YEAR(TODAY())) | D119: =B119-C119 | E119: =COUNTIFS(J4:J103,12,K4:K103,YEAR(TODAY()))
A121: 📈 ANNUAL SUMMARY | D121: 💼 INCOME BY SOURCE
A122: Total Gross Income | B122: =SUM(B108:B119) | D122: Salary | E122: =SUMIF(B4:B103,D122,D4:D103) | F122: =IFERROR(E122/SUM(D4:D103),0)
A123: Total Tax Reserved | B123: =SUM(C108:C119) | D123: Freelance/Contract | E123: =SUMIF(B4:B103,D123,D4:D103) | F123: =IFERROR(E123/SUM(D4:D103),0)
A124: Total Net Income | B124: =SUM(D108:D119) | D124: Business Revenue | E124: =SUMIF(B4:B103,D124,D4:D103) | F124: =IFERROR(E124/SUM(D4:D103),0)
A125: Best Income Month | B125: =INDEX(A108:A119,MATCH(MAX(B108:B119),B108:B119,0)) | D125: Rental Income | E125: =SUMIF(B4:B103,D125,D4:D103) | F125: =IFERROR(E125/SUM(D4:D103),0)
A126: Average Monthly Income | B126: =IFERROR(AVERAGEIF(B108:B119,">0"),0) | D126: Dividends | E126: =SUMIF(B4:B103,D126,D4:D103) | F126: =IFERROR(E126/SUM(D4:D103),0)
D127: Interest | E127: =SUMIF(B4:B103,D127,D4:D103) | F127: =IFERROR(E127/SUM(D4:D103),0)
D128: Refund | E128: =SUMIF(B4:B103,D128,D4:D103) | F128: =IFERROR(E128/SUM(D4:D103),0)
D129: Gift | E129: =SUMIF(B4:B103,D129,D4:D103) | F129: =IFERROR(E129/SUM(D4:D103),0)
D130: Side Hustle | E130: =SUMIF(B4:B103,D130,D4:D103) | F130: =IFERROR(E130/SUM(D4:D103),0)
D131: Other | E131: =SUMIF(B4:B103,D131,D4:D103) | F131: =IFERROR(E131/SUM(D4:D103),0)

Sheet Savings Goals
A1: 🎯 Savings Goals
A2: Set up to 6 savings goals below. Enter your saved amount, monthly contribution, and target date in the yellow cells — progress bars, remaining amounts, and projections update automatically.
A3: 💚 YOUR GOALS
A4: 🎯 Emergency Fund | E4: Target Amount: | F4: 10000
A5: 💰 Saved: | B5: 6500 | C5: 📆 Monthly Contribution: | D5: 300 | E5: 🗓️ Target Date: | F5: 46552 | G5: Remaining: | H5: =F4-B5
A6: =REPT("█",ROUND((IFERROR(MIN(B5/F4,1),0))*20,0))&REPT("░",20-ROUND((IFERROR(MIN(B5/F4,1),0))*20,0))&" "&TEXT(IFERROR(MIN(B5/F4,1),0),"0%")
A7: =IF(B5>=F4,"🎉 Goal reached — congratulations!","📅 On track to reach this goal around "&IF(D5<=0,"N/A (set a monthly contribution)",TEXT(TODAY()+(F4-B5)/D5*30,"MMMM YYYY"))&". 💡 To hit your "&TEXT(F5,"MMM YYYY")&" target date, save "&TEXT(IFERROR((F4-B5)/MAX(DATEDIF(TODAY(),F5,"M"),1),F4-B5),"$#,##0")&"/month.")
A9: 🎯 Vacation | E9: Target Amount: | F9: 3000
A10: 💰 Saved: | B10: 2400 | C10: 📆 Monthly Contribution: | D10: 150 | E10: 🗓️ Target Date: | F10: 46307 | G10: Remaining: | H10: =F9-B10
A11: =REPT("█",ROUND((IFERROR(MIN(B10/F9,1),0))*20,0))&REPT("░",20-ROUND((IFERROR(MIN(B10/F9,1),0))*20,0))&" "&TEXT(IFERROR(MIN(B10/F9,1),0),"0%")
A12: =IF(B10>=F9,"🎉 Goal reached — congratulations!","📅 On track to reach this goal around "&IF(D10<=0,"N/A (set a monthly contribution)",TEXT(TODAY()+(F9-B10)/D10*30,"MMMM YYYY"))&". 💡 To hit your "&TEXT(F10,"MMM YYYY")&" target date, save "&TEXT(IFERROR((F9-B10)/MAX(DATEDIF(TODAY(),F10,"M"),1),F9-B10),"$#,##0")&"/month.")
A14: 🎯 New Car | E14: Target Amount: | F14: 8000
A15: 💰 Saved: | B15: 2000 | C15: 📆 Monthly Contribution: | D15: 200 | E15: 🗓️ Target Date: | F15: 46917 | G15: Remaining: | H15: =F14-B15
A16: =REPT("█",ROUND((IFERROR(MIN(B15/F14,1),0))*20,0))&REPT("░",20-ROUND((IFERROR(MIN(B15/F14,1),0))*20,0))&" "&TEXT(IFERROR(MIN(B15/F14,1),0),"0%")
A17: =IF(B15>=F14,"🎉 Goal reached — congratulations!","📅 On track to reach this goal around "&IF(D15<=0,"N/A (set a monthly contribution)",TEXT(TODAY()+(F14-B15)/D15*30,"MMMM YYYY"))&". 💡 To hit your "&TEXT(F15,"MMM YYYY")&" target date, save "&TEXT(IFERROR((F14-B15)/MAX(DATEDIF(TODAY(),F15,"M"),1),F14-B15),"$#,##0")&"/month.")
A19: 🎯 Down Payment | E19: Target Amount: | F19: 25000
A20: 💰 Saved: | B20: 9000 | C20: 📆 Monthly Contribution: | D20: 400 | E20: 🗓️ Target Date: | F20: 47282 | G20: Remaining: | H20: =F19-B20
A21: =REPT("█",ROUND((IFERROR(MIN(B20/F19,1),0))*20,0))&REPT("░",20-ROUND((IFERROR(MIN(B20/F19,1),0))*20,0))&" "&TEXT(IFERROR(MIN(B20/F19,1),0),"0%")
A22: =IF(B20>=F19,"🎉 Goal reached — congratulations!","📅 On track to reach this goal around "&IF(D20<=0,"N/A (set a monthly contribution)",TEXT(TODAY()+(F19-B20)/D20*30,"MMMM YYYY"))&". 💡 To hit your "&TEXT(F20,"MMM YYYY")&" target date, save "&TEXT(IFERROR((F19-B20)/MAX(DATEDIF(TODAY(),F20,"M"),1),F19-B20),"$#,##0")&"/month.")
A24: 🎯 Investment Fund | E24: Target Amount: | F24: 5000
A25: 💰 Saved: | B25: 4200 | C25: 📆 Monthly Contribution: | D25: 250 | E25: 🗓️ Target Date: | F25: 46277 | G25: Remaining: | H25: =F24-B25
A26: =REPT("█",ROUND((IFERROR(MIN(B25/F24,1),0))*20,0))&REPT("░",20-ROUND((IFERROR(MIN(B25/F24,1),0))*20,0))&" "&TEXT(IFERROR(MIN(B25/F24,1),0),"0%")
A27: =IF(B25>=F24,"🎉 Goal reached — congratulations!","📅 On track to reach this goal around "&IF(D25<=0,"N/A (set a monthly contribution)",TEXT(TODAY()+(F24-B25)/D25*30,"MMMM YYYY"))&". 💡 To hit your "&TEXT(F25,"MMM YYYY")&" target date, save "&TEXT(IFERROR((F24-B25)/MAX(DATEDIF(TODAY(),F25,"M"),1),F24-B25),"$#,##0")&"/month.")
A29: 🎯 Christmas Gifts | E29: Target Amount: | F29: 1500
A30: 💰 Saved: | B30: 900 | C30: 📆 Monthly Contribution: | D30: 100 | E30: 🗓️ Target Date: | F30: 46381 | G30: Remaining: | H30: =F29-B30
A31: =REPT("█",ROUND((IFERROR(MIN(B30/F29,1),0))*20,0))&REPT("░",20-ROUND((IFERROR(MIN(B30/F29,1),0))*20,0))&" "&TEXT(IFERROR(MIN(B30/F29,1),0),"0%")
A32: =IF(B30>=F29,"🎉 Goal reached — congratulations!","📅 On track to reach this goal around "&IF(D30<=0,"N/A (set a monthly contribution)",TEXT(TODAY()+(F29-B30)/D30*30,"MMMM YYYY"))&". 💡 To hit your "&TEXT(F30,"MMM YYYY")&" target date, save "&TEXT(IFERROR((F29-B30)/MAX(DATEDIF(TODAY(),F30,"M"),1),F29-B30),"$#,##0")&"/month.")
A35: 📊 OVERALL PROGRESS
A36: Total Saved | B36: =B5+B10+B15+B20+B25+B30 | C36: Total Target | D36: =F4+F9+F14+F19+F24+F29 | E36: Total Remaining | F36: =D36-B36 | G36: Overall % | H36: =IFERROR(B36/D36,0)
A37: =REPT("█",ROUND((IFERROR(B36/D36,0))*20,0))&REPT("░",20-ROUND((IFERROR(B36/D36,0))*20,0))&" "&TEXT(IFERROR(B36/D36,0),"0%")

Sheet Debt Tracker
A1: 💳 Debt Tracker
A2: List every debt you're paying down. Enter balances, rates, and payments in the yellow cells — payoff dates, progress bars, and payoff strategies update automatically.
A3: Debt Name | B3: Debt Type | C3: Starting Balance | D3: Current Balance | E3: Interest Rate | F3: Min. Payment | G3: Extra Payment | H3: Total Payment | I3: Monthly Interest | J3: Principal Paid | K3: Est. Payoff Date | L3: Progress % | M3: Progress | N3: Payoff Date (raw)
A4: Credit Card A | B4: Credit Card | C4: 8000 | D4: 5400 | E4: 0.2299 | F4: 150 | G4: 100 | H4: =F4+G4 | I4: =D4*(E4/12) | J4: =H4-I4 | K4: =IF(D4<=0,"✅ Paid Off!",IF(J4<=0,"⚠️ Add extra payment",TEXT(N4,"YYYY-MM-DD"))) | L4: =IFERROR((C4-D4)/C4,0) | M4: =REPT("█",ROUND((IFERROR((C4-D4)/C4,0))*20,0))&REPT("░",20-ROUND((IFERROR((C4-D4)/C4,0))*20,0))&" "&TEXT(IFERROR((C4-D4)/C4,0),"0%") | N4: =IF(D4<=0,TODAY(),IF(J4<=0,DATE(2099,12,31),EDATE(TODAY(),ROUND(D4/J4,0))))
A5: Car Loan | B5: Car Loan | C5: 22000 | D5: 14500 | E5: 0.069 | F5: 380 | G5: 0 | H5: =F5+G5 | I5: =D5*(E5/12) | J5: =H5-I5 | K5: =IF(D5<=0,"✅ Paid Off!",IF(J5<=0,"⚠️ Add extra payment",TEXT(N5,"YYYY-MM-DD"))) | L5: =IFERROR((C5-D5)/C5,0) | M5: =REPT("█",ROUND((IFERROR((C5-D5)/C5,0))*20,0))&REPT("░",20-ROUND((IFERROR((C5-D5)/C5,0))*20,0))&" "&TEXT(IFERROR((C5-D5)/C5,0),"0%") | N5: =IF(D5<=0,TODAY(),IF(J5<=0,DATE(2099,12,31),EDATE(TODAY(),ROUND(D5/J5,0))))
A6: Student Loan | B6: Student Loan | C6: 30000 | D6: 24800 | E6: 0.05 | F6: 320 | G6: 0 | H6: =F6+G6 | I6: =D6*(E6/12) | J6: =H6-I6 | K6: =IF(D6<=0,"✅ Paid Off!",IF(J6<=0,"⚠️ Add extra payment",TEXT(N6,"YYYY-MM-DD"))) | L6: =IFERROR((C6-D6)/C6,0) | M6: =REPT("█",ROUND((IFERROR((C6-D6)/C6,0))*20,0))&REPT("░",20-ROUND((IFERROR((C6-D6)/C6,0))*20,0))&" "&TEXT(IFERROR((C6-D6)/C6,0),"0%") | N6: =IF(D6<=0,TODAY(),IF(J6<=0,DATE(2099,12,31),EDATE(TODAY(),ROUND(D6/J6,0))))
A7: Personal Loan | B7: Personal Loan | C7: 6000 | D7: 3100 | E7: 0.12 | F7: 180 | G7: 50 | H7: =F7+G7 | I7: =D7*(E7/12) | J7: =H7-I7 | K7: =IF(D7<=0,"✅ Paid Off!",IF(J7<=0,"⚠️ Add extra payment",TEXT(N7,"YYYY-MM-DD"))) | L7: =IFERROR((C7-D7)/C7,0) | M7: =REPT("█",ROUND((IFERROR((C7-D7)/C7,0))*20,0))&REPT("░",20-ROUND((IFERROR((C7-D7)/C7,0))*20,0))&" "&TEXT(IFERROR((C7-D7)/C7,0),"0%") | N7: =IF(D7<=0,TODAY(),IF(J7<=0,DATE(2099,12,31),EDATE(TODAY(),ROUND(D7/J7,0))))
A9: 📊 DEBT SUMMARY
A10: Total Debt | B10: =SUM(D4:D7) | C10: Total Min. Payments | D10: =SUM(F4:F7) | E10: Total Monthly Payment | F10: =SUM(H4:H7) | G10: Total Monthly Interest | H10: =SUM(I4:I7) | I10: Debt-Free Date | J10: =TEXT(MAX(N4:N7),"YYYY-MM-DD") | K10: Avg. Interest Rate | L10: =AVERAGE(E4:E7)
A12: 🏔️ AVALANCHE METHOD — Highest Interest First | H12: ⚪ SNOWBALL METHOD — Smallest Balance First
A13: Rank | B13: Debt Name | C13: Current Balance | D13: Interest Rate | H13: Rank | I13: Debt Name | J13: Current Balance | K13: Monthly Payment
A14: 1 | B14: =IFERROR(INDEX($A$4:$A$7,MATCH(D14,$E$4:$E$7,0)),"") | C14: =IFERROR(INDEX($D$4:$D$7,MATCH(D14,$E$4:$E$7,0)),"") | D14: =LARGE($E$4:$E$7,1) | H14: 1 | I14: =IFERROR(INDEX($A$4:$A$7,MATCH(J14,$D$4:$D$7,0)),"") | J14: =SMALL($D$4:$D$7,1) | K14: =IFERROR(INDEX($H$4:$H$7,MATCH(J14,$D$4:$D$7,0)),"")
A15: 2 | B15: =IFERROR(INDEX($A$4:$A$7,MATCH(D15,$E$4:$E$7,0)),"") | C15: =IFERROR(INDEX($D$4:$D$7,MATCH(D15,$E$4:$E$7,0)),"") | D15: =LARGE($E$4:$E$7,2) | H15: 2 | I15: =IFERROR(INDEX($A$4:$A$7,MATCH(J15,$D$4:$D$7,0)),"") | J15: =SMALL($D$4:$D$7,2) | K15: =IFERROR(INDEX($H$4:$H$7,MATCH(J15,$D$4:$D$7,0)),"")
A16: 3 | B16: =IFERROR(INDEX($A$4:$A$7,MATCH(D16,$E$4:$E$7,0)),"") | C16: =IFERROR(INDEX($D$4:$D$7,MATCH(D16,$E$4:$E$7,0)),"") | D16: =LARGE($E$4:$E$7,3) | H16: 3 | I16: =IFERROR(INDEX($A$4:$A$7,MATCH(J16,$D$4:$D$7,0)),"") | J16: =SMALL($D$4:$D$7,3) | K16: =IFERROR(INDEX($H$4:$H$7,MATCH(J16,$D$4:$D$7,0)),"")
A17: 4 | B17: =IFERROR(INDEX($A$4:$A$7,MATCH(D17,$E$4:$E$7,0)),"") | C17: =IFERROR(INDEX($D$4:$D$7,MATCH(D17,$E$4:$E$7,0)),"") | D17: =LARGE($E$4:$E$7,4) | H17: 4 | I17: =IFERROR(INDEX($A$4:$A$7,MATCH(J17,$D$4:$D$7,0)),"") | J17: =SMALL($D$4:$D$7,4) | K17: =IFERROR(INDEX($H$4:$H$7,MATCH(J17,$D$4:$D$7,0)),"")
A19: 💡 Avalanche saves the most money on interest over time. Snowball builds momentum with quick wins. Either way: keep paying the minimum on every debt, and put every extra dollar toward the #1 debt in your chosen method.

Sheet Sinking Funds
A1: 🫙 Sinking Funds
A2: Sinking funds are savings set aside for known upcoming expenses (car repairs, holiday gifts, annual bills). Enter your annual target and current balance for each fund — the rest updates automatically.
A3: Fund Name | B3: Category | C3: Annual Target | D3: Current Balance | E3: Suggested Monthly | F3: Remaining | G3: % Funded | H3: Progress | I3: Next Use Date
A4: Car Maintenance | B4: Auto | C4: 1200 | D4: 450 | E4: =ROUND(C4/12,2) | F4: =C4-D4 | G4: =IFERROR(D4/C4,0) | H4: =REPT("█",ROUND((IFERROR(MIN(D4/C4,1),0))*20,0))&REPT("░",20-ROUND((IFERROR(MIN(D4/C4,1),0))*20,0))&" "&TEXT(IFERROR(MIN(D4/C4,1),0),"0%") | I4: 46387
A5: Holiday Gifts | B5: Personal | C5: 800 | D5: 800 | E5: =ROUND(C5/12,2) | F5: =C5-D5 | G5: =IFERROR(D5/C5,0) | H5: =REPT("█",ROUND((IFERROR(MIN(D5/C5,1),0))*20,0))&REPT("░",20-ROUND((IFERROR(MIN(D5/C5,1),0))*20,0))&" "&TEXT(IFERROR(MIN(D5/C5,1),0),"0%") | I5: 46381
A6: Property Taxes | B6: Home | C6: 2400 | D6: 600 | E6: =ROUND(C6/12,2) | F6: =C6-D6 | G6: =IFERROR(D6/C6,0) | H6: =REPT("█",ROUND((IFERROR(MIN(D6/C6,1),0))*20,0))&REPT("░",20-ROUND((IFERROR(MIN(D6/C6,1),0))*20,0))&" "&TEXT(IFERROR(MIN(D6/C6,1),0),"0%") | I6: 46487
A7: Annual Subscriptions | B7: Subscriptions | C7: 300 | D7: 300 | E7: =ROUND(C7/12,2) | F7: =C7-D7 | G7: =IFERROR(D7/C7,0) | H7: =REPT("█",ROUND((IFERROR(MIN(D7/C7,1),0))*20,0))&REPT("░",20-ROUND((IFERROR(MIN(D7/C7,1),0))*20,0))&" "&TEXT(IFERROR(MIN(D7/C7,1),0),"0%") | I7: 46247
A8: Home Maintenance | B8: Home | C8: 1500 | D8: 375 | E8: =ROUND(C8/12,2) | F8: =C8-D8 | G8: =IFERROR(D8/C8,0) | H8: =REPT("█",ROUND((IFERROR(MIN(D8/C8,1),0))*20,0))&REPT("░",20-ROUND((IFERROR(MIN(D8/C8,1),0))*20,0))&" "&TEXT(IFERROR(MIN(D8/C8,1),0),"0%") | I8: 46367
A9: Medical / Dental | B9: Health | C9: 1000 | D9: 250 | E9: =ROUND(C9/12,2) | F9: =C9-D9 | G9: =IFERROR(D9/C9,0) | H9: =REPT("█",ROUND((IFERROR(MIN(D9/C9,1),0))*20,0))&REPT("░",20-ROUND((IFERROR(MIN(D9/C9,1),0))*20,0))&" "&TEXT(IFERROR(MIN(D9/C9,1),0),"0%") | I9: 46337
A10: Car Registration | B10: Auto | C10: 200 | D10: 200 | E10: =ROUND(C10/12,2) | F10: =C10-D10 | G10: =IFERROR(D10/C10,0) | H10: =REPT("█",ROUND((IFERROR(MIN(D10/C10,1),0))*20,0))&REPT("░",20-ROUND((IFERROR(MIN(D10/C10,1),0))*20,0))&" "&TEXT(IFERROR(MIN(D10/C10,1),0),"0%") | I10: 46247
A11: Birthday Gifts | B11: Personal | C11: 400 | D11: 100 | E11: =ROUND(C11/12,2) | F11: =C11-D11 | G11: =IFERROR(D11/C11,0) | H11: =REPT("█",ROUND((IFERROR(MIN(D11/C11,1),0))*20,0))&REPT("░",20-ROUND((IFERROR(MIN(D11/C11,1),0))*20,0))&" "&TEXT(IFERROR(MIN(D11/C11,1),0),"0%") | I11: 46277
A12: Pet Care | B12: Pets | C12: 600 | D12: 300 | E12: =ROUND(C12/12,2) | F12: =C12-D12 | G12: =IFERROR(D12/C12,0) | H12: =REPT("█",ROUND((IFERROR(MIN(D12/C12,1),0))*20,0))&REPT("░",20-ROUND((IFERROR(MIN(D12/C12,1),0))*20,0))&" "&TEXT(IFERROR(MIN(D12/C12,1),0),"0%") | I12: 46307
A13: Clothing | B13: Personal | C13: 600 | D13: 150 | E13: =ROUND(C13/12,2) | F13: =C13-D13 | G13: =IFERROR(D13/C13,0) | H13: =REPT("█",ROUND((IFERROR(MIN(D13/C13,1),0))*20,0))&REPT("░",20-ROUND((IFERROR(MIN(D13/C13,1),0))*20,0))&" "&TEXT(IFERROR(MIN(D13/C13,1),0),"0%") | I13: 46387
A14: Electronics / Tech | B14: Personal | C14: 500 | D14: 500 | E14: =ROUND(C14/12,2) | F14: =C14-D14 | G14: =IFERROR(D14/C14,0) | H14: =REPT("█",ROUND((IFERROR(MIN(D14/C14,1),0))*20,0))&REPT("░",20-ROUND((IFERROR(MIN(D14/C14,1),0))*20,0))&" "&TEXT(IFERROR(MIN(D14/C14,1),0),"0%") | I14: 46437
A15: Travel Fund | B15: Travel | C15: 2000 | D15: 800 | E15: =ROUND(C15/12,2) | F15: =C15-D15 | G15: =IFERROR(D15/C15,0) | H15: =REPT("█",ROUND((IFERROR(MIN(D15/C15,1),0))*20,0))&REPT("░",20-ROUND((IFERROR(MIN(D15/C15,1),0))*20,0))&" "&TEXT(IFERROR(MIN(D15/C15,1),0),"0%") | I15: 46367
A17: TOTAL | C17: =SUM(C4:C15) | D17: =SUM(D4:D15) | E17: =SUM(E4:E15) | F17: =SUM(F4:F15) | G17: =IFERROR(D17/C17,0) | H17: =REPT("█",ROUND((IFERROR(D17/C17,0))*20,0))&REPT("░",20-ROUND((IFERROR(D17/C17,0))*20,0))&" "&TEXT(IFERROR(D17/C17,0),"0%")

Sheet Subscriptions
A1: 🔁 Subscriptions
A2: Track every recurring subscription in one place. Set a subscription to 'No' under Active when you cancel it — totals below only count active subscriptions.
A3: Service Name | B3: Category | C3: Monthly Cost | D3: Billing Cycle | E3: Annual Cost | F3: Next Billing Date | G3: Payment Method | H3: Active?
A4: Netflix | B4: Streaming | C4: 15.49 | D4: Monthly | E4: =IFS(D4="Monthly",C4*12,D4="Annual",C4,D4="Quarterly",C4*4,D4="Weekly",C4*52,TRUE,C4*12) | F4: 46199 | G4: Credit Card | H4: Yes
A5: Spotify | B5: Streaming | C5: 11.99 | D5: Monthly | E5: =IFS(D5="Monthly",C5*12,D5="Annual",C5,D5="Quarterly",C5*4,D5="Weekly",C5*52,TRUE,C5*12) | F5: 46192 | G5: Credit Card | H5: Yes
A6: Amazon Prime | B6: Shopping | C6: 139 | D6: Annual | E6: =IFS(D6="Monthly",C6*12,D6="Annual",C6,D6="Quarterly",C6*4,D6="Weekly",C6*52,TRUE,C6*12) | F6: 46387 | G6: Credit Card | H6: Yes
A7: Disney+ | B7: Streaming | C7: 13.99 | D7: Monthly | E7: =IFS(D7="Monthly",C7*12,D7="Annual",C7,D7="Quarterly",C7*4,D7="Weekly",C7*52,TRUE,C7*12) | F7: 46205 | G7: Debit Card | H7: Yes
A8: Gym Membership | B8: Fitness | C8: 39.99 | D8: Monthly | E8: =IFS(D8="Monthly",C8*12,D8="Annual",C8,D8="Quarterly",C8*4,D8="Weekly",C8*52,TRUE,C8*12) | F8: 46188 | G8: Bank Transfer | H8: Yes
A9: iCloud Storage | B9: Software | C9: 2.99 | D9: Monthly | E9: =IFS(D9="Monthly",C9*12,D9="Annual",C9,D9="Quarterly",C9*4,D9="Weekly",C9*52,TRUE,C9*12) | F9: 46196 | G9: Credit Card | H9: Yes
A10: YouTube Premium | B10: Streaming | C10: 13.99 | D10: Monthly | E10: =IFS(D10="Monthly",C10*12,D10="Annual",C10,D10="Quarterly",C10*4,D10="Weekly",C10*52,TRUE,C10*12) | F10: 46209 | G10: Credit Card | H10: Yes
A11: Adobe Creative Cloud | B11: Software | C11: 54.99 | D11: Monthly | E11: =IFS(D11="Monthly",C11*12,D11="Annual",C11,D11="Quarterly",C11*4,D11="Weekly",C11*52,TRUE,C11*12) | F11: 46201 | G11: Credit Card | H11: Yes
A12: Microsoft 365 | B12: Software | C12: 99 | D12: Annual | E12: =IFS(D12="Monthly",C12*12,D12="Annual",C12,D12="Quarterly",C12*4,D12="Weekly",C12*52,TRUE,C12*12) | F12: 46307 | G12: Credit Card | H12: Yes
A13: Hulu | B13: Streaming | C13: 7.99 | D13: Monthly | E13: =IFS(D13="Monthly",C13*12,D13="Annual",C13,D13="Quarterly",C13*4,D13="Weekly",C13*52,TRUE,C13*12) | F13: 46214 | G13: Debit Card | H13: No
A14: Audible | B14: Entertainment | C14: 14.95 | D14: Monthly | E14: =IFS(D14="Monthly",C14*12,D14="Annual",C14,D14="Quarterly",C14*4,D14="Weekly",C14*52,TRUE,C14*12) | F14: 46195 | G14: Credit Card | H14: Yes
A15: Domain / Hosting | B15: Software | C15: 180 | D15: Annual | E15: =IFS(D15="Monthly",C15*12,D15="Annual",C15,D15="Quarterly",C15*4,D15="Weekly",C15*52,TRUE,C15*12) | F15: 46437 | G15: PayPal | H15: Yes
A17: 📊 SUBSCRIPTION SUMMARY
A18: Active Subscriptions | B18: =COUNTIF(H4:H15,"Yes") | C18: Monthly Cost (Active) | D18: =SUMIF(H4:H15,"Yes",C4:C15) | E18: Annual Cost (Active) | F18: =SUMIF(H4:H15,"Yes",E4:E15) | G18: Cancelled (Annual Savings) | H18: =SUMIF(H4:H15,"No",E4:E15)

Sheet Bills Calendar
A1: 📅 Bills Calendar
A2: List every recurring bill with its due day of the month. Mark a bill 'Yes' under Paid? once you've paid it — the Status column and summary below update automatically.
A3: Bill Name | B3: Category | C3: Due Day | D3: Amount | E3: Payment Method | F3: Auto-Pay? | G3: Paid? | H3: Due Date | I3: Days Until Due | J3: Notes | K3: Date Paid | L3: Status
A4: Rent / Mortgage | B4: Housing | C4: 1 | D4: 1450 | E4: Bank Transfer | F4: Yes | G4: Yes | H4: =DATE(YEAR(TODAY()),MONTH(TODAY()),C4) | I4: =H4-TODAY() | K4: 46185 | L4: =IF(G4="Yes","✅ Paid",IF(I4<0,"🔴 Overdue",IF(I4<=3,"⚠️ Due Soon","📅 Upcoming")))
A5: Electricity | B5: Utilities | C5: 5 | D5: 120 | E5: Debit Card | F5: Yes | G5: Yes | H5: =DATE(YEAR(TODAY()),MONTH(TODAY()),C5) | I5: =H5-TODAY() | K5: 46185 | L5: =IF(G5="Yes","✅ Paid",IF(I5<0,"🔴 Overdue",IF(I5<=3,"⚠️ Due Soon","📅 Upcoming")))
A6: Water | B6: Utilities | C6: 7 | D6: 45 | E6: Debit Card | F6: No | G6: No | H6: =DATE(YEAR(TODAY()),MONTH(TODAY()),C6) | I6: =H6-TODAY() | L6: =IF(G6="Yes","✅ Paid",IF(I6<0,"🔴 Overdue",IF(I6<=3,"⚠️ Due Soon","📅 Upcoming")))
A7: Internet | B7: Utilities | C7: 10 | D7: 65 | E7: Credit Card | F7: Yes | G7: Yes | H7: =DATE(YEAR(TODAY()),MONTH(TODAY()),C7) | I7: =H7-TODAY() | K7: 46185 | L7: =IF(G7="Yes","✅ Paid",IF(I7<0,"🔴 Overdue",IF(I7<=3,"⚠️ Due Soon","📅 Upcoming")))
A8: Phone | B8: Utilities | C8: 12 | D8: 85 | E8: Credit Card | F8: Yes | G8: No | H8: =DATE(YEAR(TODAY()),MONTH(TODAY()),C8) | I8: =H8-TODAY() | L8: =IF(G8="Yes","✅ Paid",IF(I8<0,"🔴 Overdue",IF(I8<=3,"⚠️ Due Soon","📅 Upcoming")))
A9: Car Insurance | B9: Insurance | C9: 15 | D9: 110 | E9: Bank Transfer | F9: Yes | G9: No | H9: =DATE(YEAR(TODAY()),MONTH(TODAY()),C9) | I9: =H9-TODAY() | L9: =IF(G9="Yes","✅ Paid",IF(I9<0,"🔴 Overdue",IF(I9<=3,"⚠️ Due Soon","📅 Upcoming")))
A10: Health Insurance | B10: Insurance | C10: 1 | D10: 320 | E10: Bank Transfer | F10: Yes | G10: Yes | H10: =DATE(YEAR(TODAY()),MONTH(TODAY()),C10) | I10: =H10-TODAY() | K10: 46185 | L10: =IF(G10="Yes","✅ Paid",IF(I10<0,"🔴 Overdue",IF(I10<=3,"⚠️ Due Soon","📅 Upcoming")))
A11: Car Payment | B11: Debt Payment | C11: 20 | D11: 380 | E11: Bank Transfer | F11: Yes | G11: No | H11: =DATE(YEAR(TODAY()),MONTH(TODAY()),C11) | I11: =H11-TODAY() | L11: =IF(G11="Yes","✅ Paid",IF(I11<0,"🔴 Overdue",IF(I11<=3,"⚠️ Due Soon","📅 Upcoming")))
A12: Student Loan Payment | B12: Debt Payment | C12: 25 | D12: 320 | E12: Bank Transfer | F12: Yes | G12: No | H12: =DATE(YEAR(TODAY()),MONTH(TODAY()),C12) | I12: =H12-TODAY() | L12: =IF(G12="Yes","✅ Paid",IF(I12<0,"🔴 Overdue",IF(I12<=3,"⚠️ Due Soon","📅 Upcoming")))
A13: Credit Card Payment | B13: Debt Payment | C13: 28 | D13: 150 | E13: Bank Transfer | F13: No | G13: No | H13: =DATE(YEAR(TODAY()),MONTH(TODAY()),C13) | I13: =H13-TODAY() | L13: =IF(G13="Yes","✅ Paid",IF(I13<0,"🔴 Overdue",IF(I13<=3,"⚠️ Due Soon","📅 Upcoming")))
A14: Streaming Bundle | B14: Subscriptions | C14: 3 | D14: 45 | E14: Credit Card | F14: Yes | G14: Yes | H14: =DATE(YEAR(TODAY()),MONTH(TODAY()),C14) | I14: =H14-TODAY() | K14: 46185 | L14: =IF(G14="Yes","✅ Paid",IF(I14<0,"🔴 Overdue",IF(I14<=3,"⚠️ Due Soon","📅 Upcoming")))
A15: Gym Membership | B15: Personal Care | C15: 1 | D15: 40 | E15: Bank Transfer | F15: Yes | G15: Yes | H15: =DATE(YEAR(TODAY()),MONTH(TODAY()),C15) | I15: =H15-TODAY() | K15: 46185 | L15: =IF(G15="Yes","✅ Paid",IF(I15<0,"🔴 Overdue",IF(I15<=3,"⚠️ Due Soon","📅 Upcoming")))
A16: Trash / Recycling | B16: Utilities | C16: 18 | D16: 25 | E16: Debit Card | F16: No | G16: No | H16: =DATE(YEAR(TODAY()),MONTH(TODAY()),C16) | I16: =H16-TODAY() | L16: =IF(G16="Yes","✅ Paid",IF(I16<0,"🔴 Overdue",IF(I16<=3,"⚠️ Due Soon","📅 Upcoming")))
A17: Home / Renters Insurance | B17: Insurance | C17: 1 | D17: 35 | E17: Bank Transfer | F17: Yes | G17: Yes | H17: =DATE(YEAR(TODAY()),MONTH(TODAY()),C17) | I17: =H17-TODAY() | K17: 46185 | L17: =IF(G17="Yes","✅ Paid",IF(I17<0,"🔴 Overdue",IF(I17<=3,"⚠️ Due Soon","📅 Upcoming")))
A18: Childcare | B18: Kids | C18: 1 | D18: 850 | E18: Bank Transfer | F18: No | G18: Yes | H18: =DATE(YEAR(TODAY()),MONTH(TODAY()),C18) | I18: =H18-TODAY() | K18: 46185 | L18: =IF(G18="Yes","✅ Paid",IF(I18<0,"🔴 Overdue",IF(I18<=3,"⚠️ Due Soon","📅 Upcoming")))
A20: 📊 BILLS SUMMARY
A21: Total Monthly Bills | B21: =SUM(D4:D18) | C21: Bills Paid | D21: =COUNTIF(G4:G18,"Yes") | E21: Bills Remaining | F21: =COUNTIF(G4:G18,"No") | G21: Overdue | H21: =COUNTIF(L4:L18,"🔴 Overdue") | I21: Due Soon (≤3 days) | J21: =COUNTIF(L4:L18,"⚠️ Due Soon")

Sheet Annual Overview
A1: 📈 Annual Overview
A2: A year-at-a-glance view of your income, expenses, and savings — built automatically from your Income Tracker and Expense Tracker.
A3: ="📊 YEAR-TO-DATE SUMMARY — "&TEXT(TODAY(),"YYYY")
A4: Total Income (YTD) | B4: Total Expenses (YTD) | C4: Net Savings (YTD) | D4: Savings Rate (YTD) | E4: Avg Monthly Income | F4: Avg Monthly Expenses
A5: =SUM(B9:B20) | B5: =SUM(C9:C20) | C5: =A5-B5 | D5: =IFERROR(C5/A5,0) | E5: =AVERAGE(B9:B20) | F5: =AVERAGE(C9:C20)
A7: 📅 MONTHLY BREAKDOWN
A8: Month | B8: Income | C8: Expenses | D8: Net | E8: Savings Rate | F8: % of Income Spent
A9: January | B9: =SUMIFS('Income Tracker'!G4:G103,'Income Tracker'!J4:J103,1,'Income Tracker'!K4:K103,YEAR(TODAY())) | C9: =SUMIFS('Expense Tracker'!E4:E503,'Expense Tracker'!L4:L503,1,'Expense Tracker'!M4:M503,YEAR(TODAY())) | D9: =B9-C9 | E9: =IFERROR(D9/B9,0) | F9: =REPT("█",ROUND((IFERROR(MIN(C9/B9,1),0))*20,0))&REPT("░",20-ROUND((IFERROR(MIN(C9/B9,1),0))*20,0))&" "&TEXT(IFERROR(MIN(C9/B9,1),0),"0%")
A10: February | B10: =SUMIFS('Income Tracker'!G4:G103,'Income Tracker'!J4:J103,2,'Income Tracker'!K4:K103,YEAR(TODAY())) | C10: =SUMIFS('Expense Tracker'!E4:E503,'Expense Tracker'!L4:L503,2,'Expense Tracker'!M4:M503,YEAR(TODAY())) | D10: =B10-C10 | E10: =IFERROR(D10/B10,0) | F10: =REPT("█",ROUND((IFERROR(MIN(C10/B10,1),0))*20,0))&REPT("░",20-ROUND((IFERROR(MIN(C10/B10,1),0))*20,0))&" "&TEXT(IFERROR(MIN(C10/B10,1),0),"0%")
A11: March | B11: =SUMIFS('Income Tracker'!G4:G103,'Income Tracker'!J4:J103,3,'Income Tracker'!K4:K103,YEAR(TODAY())) | C11: =SUMIFS('Expense Tracker'!E4:E503,'Expense Tracker'!L4:L503,3,'Expense Tracker'!M4:M503,YEAR(TODAY())) | D11: =B11-C11 | E11: =IFERROR(D11/B11,0) | F11: =REPT("█",ROUND((IFERROR(MIN(C11/B11,1),0))*20,0))&REPT("░",20-ROUND((IFERROR(MIN(C11/B11,1),0))*20,0))&" "&TEXT(IFERROR(MIN(C11/B11,1),0),"0%")
A12: April | B12: =SUMIFS('Income Tracker'!G4:G103,'Income Tracker'!J4:J103,4,'Income Tracker'!K4:K103,YEAR(TODAY())) | C12: =SUMIFS('Expense Tracker'!E4:E503,'Expense Tracker'!L4:L503,4,'Expense Tracker'!M4:M503,YEAR(TODAY())) | D12: =B12-C12 | E12: =IFERROR(D12/B12,0) | F12: =REPT("█",ROUND((IFERROR(MIN(C12/B12,1),0))*20,0))&REPT("░",20-ROUND((IFERROR(MIN(C12/B12,1),0))*20,0))&" "&TEXT(IFERROR(MIN(C12/B12,1),0),"0%")
A13: May | B13: =SUMIFS('Income Tracker'!G4:G103,'Income Tracker'!J4:J103,5,'Income Tracker'!K4:K103,YEAR(TODAY())) | C13: =SUMIFS('Expense Tracker'!E4:E503,'Expense Tracker'!L4:L503,5,'Expense Tracker'!M4:M503,YEAR(TODAY())) | D13: =B13-C13 | E13: =IFERROR(D13/B13,0) | F13: =REPT("█",ROUND((IFERROR(MIN(C13/B13,1),0))*20,0))&REPT("░",20-ROUND((IFERROR(MIN(C13/B13,1),0))*20,0))&" "&TEXT(IFERROR(MIN(C13/B13,1),0),"0%")
A14: June | B14: =SUMIFS('Income Tracker'!G4:G103,'Income Tracker'!J4:J103,6,'Income Tracker'!K4:K103,YEAR(TODAY())) | C14: =SUMIFS('Expense Tracker'!E4:E503,'Expense Tracker'!L4:L503,6,'Expense Tracker'!M4:M503,YEAR(TODAY())) | D14: =B14-C14 | E14: =IFERROR(D14/B14,0) | F14: =REPT("█",ROUND((IFERROR(MIN(C14/B14,1),0))*20,0))&REPT("░",20-ROUND((IFERROR(MIN(C14/B14,1),0))*20,0))&" "&TEXT(IFERROR(MIN(C14/B14,1),0),"0%")
A15: July | B15: =SUMIFS('Income Tracker'!G4:G103,'Income Tracker'!J4:J103,7,'Income Tracker'!K4:K103,YEAR(TODAY())) | C15: =SUMIFS('Expense Tracker'!E4:E503,'Expense Tracker'!L4:L503,7,'Expense Tracker'!M4:M503,YEAR(TODAY())) | D15: =B15-C15 | E15: =IFERROR(D15/B15,0) | F15: =REPT("█",ROUND((IFERROR(MIN(C15/B15,1),0))*20,0))&REPT("░",20-ROUND((IFERROR(MIN(C15/B15,1),0))*20,0))&" "&TEXT(IFERROR(MIN(C15/B15,1),0),"0%")
A16: August | B16: =SUMIFS('Income Tracker'!G4:G103,'Income Tracker'!J4:J103,8,'Income Tracker'!K4:K103,YEAR(TODAY())) | C16: =SUMIFS('Expense Tracker'!E4:E503,'Expense Tracker'!L4:L503,8,'Expense Tracker'!M4:M503,YEAR(TODAY())) | D16: =B16-C16 | E16: =IFERROR(D16/B16,0) | F16: =REPT("█",ROUND((IFERROR(MIN(C16/B16,1),0))*20,0))&REPT("░",20-ROUND((IFERROR(MIN(C16/B16,1),0))*20,0))&" "&TEXT(IFERROR(MIN(C16/B16,1),0),"0%")
A17: September | B17: =SUMIFS('Income Tracker'!G4:G103,'Income Tracker'!J4:J103,9,'Income Tracker'!K4:K103,YEAR(TODAY())) | C17: =SUMIFS('Expense Tracker'!E4:E503,'Expense Tracker'!L4:L503,9,'Expense Tracker'!M4:M503,YEAR(TODAY())) | D17: =B17-C17 | E17: =IFERROR(D17/B17,0) | F17: =REPT("█",ROUND((IFERROR(MIN(C17/B17,1),0))*20,0))&REPT("░",20-ROUND((IFERROR(MIN(C17/B17,1),0))*20,0))&" "&TEXT(IFERROR(MIN(C17/B17,1),0),"0%")
A18: October | B18: =SUMIFS('Income Tracker'!G4:G103,'Income Tracker'!J4:J103,10,'Income Tracker'!K4:K103,YEAR(TODAY())) | C18: =SUMIFS('Expense Tracker'!E4:E503,'Expense Tracker'!L4:L503,10,'Expense Tracker'!M4:M503,YEAR(TODAY())) | D18: =B18-C18 | E18: =IFERROR(D18/B18,0) | F18: =REPT("█",ROUND((IFERROR(MIN(C18/B18,1),0))*20,0))&REPT("░",20-ROUND((IFERROR(MIN(C18/B18,1),0))*20,0))&" "&TEXT(IFERROR(MIN(C18/B18,1),0),"0%")
A19: November | B19: =SUMIFS('Income Tracker'!G4:G103,'Income Tracker'!J4:J103,11,'Income Tracker'!K4:K103,YEAR(TODAY())) | C19: =SUMIFS('Expense Tracker'!E4:E503,'Expense Tracker'!L4:L503,11,'Expense Tracker'!M4:M503,YEAR(TODAY())) | D19: =B19-C19 | E19: =IFERROR(D19/B19,0) | F19: =REPT("█",ROUND((IFERROR(MIN(C19/B19,1),0))*20,0))&REPT("░",20-ROUND((IFERROR(MIN(C19/B19,1),0))*20,0))&" "&TEXT(IFERROR(MIN(C19/B19,1),0),"0%")
A20: December | B20: =SUMIFS('Income Tracker'!G4:G103,'Income Tracker'!J4:J103,12,'Income Tracker'!K4:K103,YEAR(TODAY())) | C20: =SUMIFS('Expense Tracker'!E4:E503,'Expense Tracker'!L4:L503,12,'Expense Tracker'!M4:M503,YEAR(TODAY())) | D20: =B20-C20 | E20: =IFERROR(D20/B20,0) | F20: =REPT("█",ROUND((IFERROR(MIN(C20/B20,1),0))*20,0))&REPT("░",20-ROUND((IFERROR(MIN(C20/B20,1),0))*20,0))&" "&TEXT(IFERROR(MIN(C20/B20,1),0),"0%")
A21: TOTAL | B21: =SUM(B9:B20) | C21: =SUM(C9:C20) | D21: =B21-C21 | E21: =IFERROR(D21/B21,0) | F21: =REPT("█",ROUND((IFERROR(MIN(C21/B21,1),0))*20,0))&REPT("░",20-ROUND((IFERROR(MIN(C21/B21,1),0))*20,0))&" "&TEXT(IFERROR(MIN(C21/B21,1),0),"0%")
A23: 📊 SPENDING BY CATEGORY (YEAR)
A24: Category | B24: Annual Total | C24: % of Annual Spending | D24: Avg Monthly
A25: Housing | B25: =SUMIFS('Expense Tracker'!E4:E503,'Expense Tracker'!C4:C503,A25,'Expense Tracker'!M4:M503,YEAR(TODAY())) | C25: =IFERROR(B25/$C$21,0) | D25: =B25/12 | E25: =REPT("█",ROUND((IFERROR(B25/MAX($B$25:$B$42),0))*20,0))&REPT("░",20-ROUND((IFERROR(B25/MAX($B$25:$B$42),0))*20,0))&" "&TEXT(IFERROR(B25/MAX($B$25:$B$42),0),"0%")
A26: Food & Dining | B26: =SUMIFS('Expense Tracker'!E4:E503,'Expense Tracker'!C4:C503,A26,'Expense Tracker'!M4:M503,YEAR(TODAY())) | C26: =IFERROR(B26/$C$21,0) | D26: =B26/12 | E26: =REPT("█",ROUND((IFERROR(B26/MAX($B$25:$B$42),0))*20,0))&REPT("░",20-ROUND((IFERROR(B26/MAX($B$25:$B$42),0))*20,0))&" "&TEXT(IFERROR(B26/MAX($B$25:$B$42),0),"0%")
A27: Transportation | B27: =SUMIFS('Expense Tracker'!E4:E503,'Expense Tracker'!C4:C503,A27,'Expense Tracker'!M4:M503,YEAR(TODAY())) | C27: =IFERROR(B27/$C$21,0) | D27: =B27/12 | E27: =REPT("█",ROUND((IFERROR(B27/MAX($B$25:$B$42),0))*20,0))&REPT("░",20-ROUND((IFERROR(B27/MAX($B$25:$B$42),0))*20,0))&" "&TEXT(IFERROR(B27/MAX($B$25:$B$42),0),"0%")
A28: Entertainment | B28: =SUMIFS('Expense Tracker'!E4:E503,'Expense Tracker'!C4:C503,A28,'Expense Tracker'!M4:M503,YEAR(TODAY())) | C28: =IFERROR(B28/$C$21,0) | D28: =B28/12 | E28: =REPT("█",ROUND((IFERROR(B28/MAX($B$25:$B$42),0))*20,0))&REPT("░",20-ROUND((IFERROR(B28/MAX($B$25:$B$42),0))*20,0))&" "&TEXT(IFERROR(B28/MAX($B$25:$B$42),0),"0%")
A29: Shopping | B29: =SUMIFS('Expense Tracker'!E4:E503,'Expense Tracker'!C4:C503,A29,'Expense Tracker'!M4:M503,YEAR(TODAY())) | C29: =IFERROR(B29/$C$21,0) | D29: =B29/12 | E29: =REPT("█",ROUND((IFERROR(B29/MAX($B$25:$B$42),0))*20,0))&REPT("░",20-ROUND((IFERROR(B29/MAX($B$25:$B$42),0))*20,0))&" "&TEXT(IFERROR(B29/MAX($B$25:$B$42),0),"0%")
A30: Healthcare | B30: =SUMIFS('Expense Tracker'!E4:E503,'Expense Tracker'!C4:C503,A30,'Expense Tracker'!M4:M503,YEAR(TODAY())) | C30: =IFERROR(B30/$C$21,0) | D30: =B30/12 | E30: =REPT("█",ROUND((IFERROR(B30/MAX($B$25:$B$42),0))*20,0))&REPT("░",20-ROUND((IFERROR(B30/MAX($B$25:$B$42),0))*20,0))&" "&TEXT(IFERROR(B30/MAX($B$25:$B$42),0),"0%")
A31: Utilities | B31: =SUMIFS('Expense Tracker'!E4:E503,'Expense Tracker'!C4:C503,A31,'Expense Tracker'!M4:M503,YEAR(TODAY())) | C31: =IFERROR(B31/$C$21,0) | D31: =B31/12 | E31: =REPT("█",ROUND((IFERROR(B31/MAX($B$25:$B$42),0))*20,0))&REPT("░",20-ROUND((IFERROR(B31/MAX($B$25:$B$42),0))*20,0))&" "&TEXT(IFERROR(B31/MAX($B$25:$B$42),0),"0%")
A32: Education | B32: =SUMIFS('Expense Tracker'!E4:E503,'Expense Tracker'!C4:C503,A32,'Expense Tracker'!M4:M503,YEAR(TODAY())) | C32: =IFERROR(B32/$C$21,0) | D32: =B32/12 | E32: =REPT("█",ROUND((IFERROR(B32/MAX($B$25:$B$42),0))*20,0))&REPT("░",20-ROUND((IFERROR(B32/MAX($B$25:$B$42),0))*20,0))&" "&TEXT(IFERROR(B32/MAX($B$25:$B$42),0),"0%")
A33: Personal Care | B33: =SUMIFS('Expense Tracker'!E4:E503,'Expense Tracker'!C4:C503,A33,'Expense Tracker'!M4:M503,YEAR(TODAY())) | C33: =IFERROR(B33/$C$21,0) | D33: =B33/12 | E33: =REPT("█",ROUND((IFERROR(B33/MAX($B$25:$B$42),0))*20,0))&REPT("░",20-ROUND((IFERROR(B33/MAX($B$25:$B$42),0))*20,0))&" "&TEXT(IFERROR(B33/MAX($B$25:$B$42),0),"0%")
A34: Savings | B34: =SUMIFS('Expense Tracker'!E4:E503,'Expense Tracker'!C4:C503,A34,'Expense Tracker'!M4:M503,YEAR(TODAY())) | C34: =IFERROR(B34/$C$21,0) | D34: =B34/12 | E34: =REPT("█",ROUND((IFERROR(B34/MAX($B$25:$B$42),0))*20,0))&REPT("░",20-ROUND((IFERROR(B34/MAX($B$25:$B$42),0))*20,0))&" "&TEXT(IFERROR(B34/MAX($B$25:$B$42),0),"0%")
A35: Investments | B35: =SUMIFS('Expense Tracker'!E4:E503,'Expense Tracker'!C4:C503,A35,'Expense Tracker'!M4:M503,YEAR(TODAY())) | C35: =IFERROR(B35/$C$21,0) | D35: =B35/12 | E35: =REPT("█",ROUND((IFERROR(B35/MAX($B$25:$B$42),0))*20,0))&REPT("░",20-ROUND((IFERROR(B35/MAX($B$25:$B$42),0))*20,0))&" "&TEXT(IFERROR(B35/MAX($B$25:$B$42),0),"0%")
A36: Debt Payment | B36: =SUMIFS('Expense Tracker'!E4:E503,'Expense Tracker'!C4:C503,A36,'Expense Tracker'!M4:M503,YEAR(TODAY())) | C36: =IFERROR(B36/$C$21,0) | D36: =B36/12 | E36: =REPT("█",ROUND((IFERROR(B36/MAX($B$25:$B$42),0))*20,0))&REPT("░",20-ROUND((IFERROR(B36/MAX($B$25:$B$42),0))*20,0))&" "&TEXT(IFERROR(B36/MAX($B$25:$B$42),0),"0%")
A37: Kids | B37: =SUMIFS('Expense Tracker'!E4:E503,'Expense Tracker'!C4:C503,A37,'Expense Tracker'!M4:M503,YEAR(TODAY())) | C37: =IFERROR(B37/$C$21,0) | D37: =B37/12 | E37: =REPT("█",ROUND((IFERROR(B37/MAX($B$25:$B$42),0))*20,0))&REPT("░",20-ROUND((IFERROR(B37/MAX($B$25:$B$42),0))*20,0))&" "&TEXT(IFERROR(B37/MAX($B$25:$B$42),0),"0%")
A38: Pets | B38: =SUMIFS('Expense Tracker'!E4:E503,'Expense Tracker'!C4:C503,A38,'Expense Tracker'!M4:M503,YEAR(TODAY())) | C38: =IFERROR(B38/$C$21,0) | D38: =B38/12 | E38: =REPT("█",ROUND((IFERROR(B38/MAX($B$25:$B$42),0))*20,0))&REPT("░",20-ROUND((IFERROR(B38/MAX($B$25:$B$42),0))*20,0))&" "&TEXT(IFERROR(B38/MAX($B$25:$B$42),0),"0%")
A39: Travel | B39: =SUMIFS('Expense Tracker'!E4:E503,'Expense Tracker'!C4:C503,A39,'Expense Tracker'!M4:M503,YEAR(TODAY())) | C39: =IFERROR(B39/$C$21,0) | D39: =B39/12 | E39: =REPT("█",ROUND((IFERROR(B39/MAX($B$25:$B$42),0))*20,0))&REPT("░",20-ROUND((IFERROR(B39/MAX($B$25:$B$42),0))*20,0))&" "&TEXT(IFERROR(B39/MAX($B$25:$B$42),0),"0%")
A40: Subscriptions | B40: =SUMIFS('Expense Tracker'!E4:E503,'Expense Tracker'!C4:C503,A40,'Expense Tracker'!M4:M503,YEAR(TODAY())) | C40: =IFERROR(B40/$C$21,0) | D40: =B40/12 | E40: =REPT("█",ROUND((IFERROR(B40/MAX($B$25:$B$42),0))*20,0))&REPT("░",20-ROUND((IFERROR(B40/MAX($B$25:$B$42),0))*20,0))&" "&TEXT(IFERROR(B40/MAX($B$25:$B$42),0),"0%")
A41: Insurance | B41: =SUMIFS('Expense Tracker'!E4:E503,'Expense Tracker'!C4:C503,A41,'Expense Tracker'!M4:M503,YEAR(TODAY())) | C41: =IFERROR(B41/$C$21,0) | D41: =B41/12 | E41: =REPT("█",ROUND((IFERROR(B41/MAX($B$25:$B$42),0))*20,0))&REPT("░",20-ROUND((IFERROR(B41/MAX($B$25:$B$42),0))*20,0))&" "&TEXT(IFERROR(B41/MAX($B$25:$B$42),0),"0%")
A42: Other | B42: =SUMIFS('Expense Tracker'!E4:E503,'Expense Tracker'!C4:C503,A42,'Expense Tracker'!M4:M503,YEAR(TODAY())) | C42: =IFERROR(B42/$C$21,0) | D42: =B42/12 | E42: =REPT("█",ROUND((IFERROR(B42/MAX($B$25:$B$42),0))*20,0))&REPT("░",20-ROUND((IFERROR(B42/MAX($B$25:$B$42),0))*20,0))&" "&TEXT(IFERROR(B42/MAX($B$25:$B$42),0),"0%")
